Workbook

Sheet Übersicht
A1: Finanzplanung Theo & Jule
A2: Monatsübersicht über Einkünfte, Kosten und die Entwicklung der drei Konten. Alles rechnet sich aus den Blättern „Monatlich“, „Einmalig“ und „Annahmen“ – auf diesem Blatt bitte nichts überschreiben.
A4: Sparziel | C4: =Annahmen!C7 -> 35000 | E4: Netto Haushalt / Monat | G4: =Annahmen!C55+Annahmen!D55 -> 7522.3205
A5: Zielmonat | C5: =Annahmen!C8 -> 46569 | E5: Ausgaben / Monat (1. Monat) | G5: =$M$11 -> 4000
A6: Gesamtvermögen im Zielmonat | C6: =IFERROR(INDEX($T$11:$T$34,MATCH($C$5,$A$11:$A$34,0)),"außerhalb des Zeitraums") -> 86145.526 | E6: Sparrate / Monat (1. Monat) | G6: =$N$11 -> 53522.321
A7: Status | C7: =IF(ISNUMBER($C$6),IF($C$6>=$C$4,"Ziel erreicht – Puffer "&TEXT($C$6-$C$4,"#,##0")&" €","Es fehlen "&TEXT($C$4-$C$6,"#,##0")&" €"),"–") -> Ziel erreicht – Puffer 51145,526 €
B9: Einnahmen | H9: Ausgaben | N9: Verteilung | Q9: Kontostände
A10: Monat | B10: Netto Theo | C10: Netto Jule | D10: Sonstige Theo | E10: Sonstige Jule | F10: Sonstige Gemeinsam | G10: Einnahmen gesamt | H10: Budget Theo | I10: Budget Jule | J10: Weitere Theo | K10: Weitere Jule | L10: Kosten Gemeinsam | M10: Ausgaben gesamt | N10: Überschuss | O10: → Gemeinsam von Theo | P10: → Gemeinsam von Jule | Q10: Konto Theo | R10: Konto Jule | S10: Konto Gemeinsam | T10: Gesamtvermögen
A11: =Annahmen!C5 -> 46266 | B11: =Annahmen!C55 -> 4916.8605 | C11: =Annahmen!D55 -> 2605.46 | D11: =SUMIFS(Monatlich!$E$4:$E$63,Monatlich!$A$4:$A$63,"Ja",Monatlich!$H$4:$H$63,"Theo",Monatlich!$D$4:$D$63,"Einnahme",Monatlich!$J$4:$J$63,"<="&$A11,Monatlich!$K$4:$K$63,">="&$A11)+SUMIFS(Einmalig!$E$4:$E$43,Einmalig!$A$4:$A$43,"Ja",Einmalig!$G$4:$G$43,"Theo",Einmalig!$D$4:$D$43,"Einnahme",Einmalig!$I$4:$I$43,$A11) -> 50000 | E11: =SUMIFS(Monatlich!$E$4:$E$63,Monatlich!$A$4:$A$63,"Ja",Monatlich!$H$4:$H$63,"Jule",Monatlich!$D$4:$D$63,"Einnahme",Monatlich!$J$4:$J$63,"<="&$A11,Monatlich!$K$4:$K$63,">="&$A11)+SUMIFS(Einmalig!$E$4:$E$43,Einmalig!$A$4:$A$43,"Ja",Einmalig!$G$4:$G$43,"Jule",Einmalig!$D$4:$D$43,"Einnahme",Einmalig!$I$4:$I$43,$A11) -> 0 | F11: =SUMIFS(Monatlich!$E$4:$E$63,Monatlich!$A$4:$A$63,"Ja",Monatlich!$H$4:$H$63,"Gemeinsam",Monatlich!$D$4:$D$63,"Einnahme",Monatlich!$J$4:$J$63,"<="&$A11,Monatlich!$K$4:$K$63,">="&$A11)+SUMIFS(Einmalig!$E$4:$E$43,Einmalig!$A$4:$A$43,"Ja",Einmalig!$G$4:$G$43,"Gemeinsam",Einmalig!$D$4:$D$43,"Einnahme",Einmalig!$I$4:$I$43,$A11) -> 0 | G11: =SUM(B11:F11) -> 57522.321 | H11: =Annahmen!C17 -> 750 | I11: =Annahmen!C18 -> 750 | J11: =SUMIFS(Monatlich!$E$4:$E$63,Monatlich!$A$4:$A$63,"Ja",Monatlich!$H$4:$H$63,"Theo",Monatlich!$D$4:$D$63,"Ausgabe",Monatlich!$J$4:$J$63,"<="&$A11,Monatlich!$K$4:$K$63,">="&$A11)+SUMIFS(Einmalig!$E$4:$E$43,Einmalig!$A$4:$A$43,"Ja",Einmalig!$G$4:$G$43,"Theo",Einmalig!$D$4:$D$43,"Ausgabe",Einmalig!$I$4:$I$43,$A11) -> 0 | K11: =SUMIFS(Monatlich!$E$4:$E$63,Monatlich!$A$4:$A$63,"Ja",Monatlich!$H$4:$H$63,"Jule",Monatlich!$D$4:$D$63,"Ausgabe",Monatlich!$J$4:$J$63,"<="&$A11,Monatlich!$K$4:$K$63,">="&$A11)+SUMIFS(Einmalig!$E$4:$E$43,Einmalig!$A$4:$A$43,"Ja",Einmalig!$G$4:$G$43,"Jule",Einmalig!$D$4:$D$43,"Ausgabe",Einmalig!$I$4:$I$43,$A11) -> 0 | L11: =SUMIFS(Monatlich!$E$4:$E$63,Monatlich!$A$4:$A$63,"Ja",Monatlich!$H$4:$H$63,"Gemeinsam",Monatlich!$D$4:$D$63,"Ausgabe",Monatlich!$J$4:$J$63,"<="&$A11,Monatlich!$K$4:$K$63,">="&$A11)+SUMIFS(Einmalig!$E$4:$E$43,Einmalig!$A$4:$A$43,"Ja",Einmalig!$G$4:$G$43,"Gemeinsam",Einmalig!$D$4:$D$43,"Ausgabe",Einmalig!$I$4:$I$43,$A11) -> 2500 | M11: =SUM(H11:L11) -> 4000 | N11: =G11-M11 -> 53522.321 | O11: =MAX(0,(Annahmen!C11+B11+D11-H11-J11)-Annahmen!C19) -> 50166.861 | P11: =MAX(0,(Annahmen!C12+C11+E11-I11-K11)-Annahmen!C20) -> 2355.46 | Q11: =(Annahmen!C11+B11+D11-H11-J11)-O11 -> 0 | R11: =(Annahmen!C12+C11+E11-I11-K11)-P11 -> 0 | S11: =Annahmen!C13+O11+P11+F11-L11 -> 50022.321 | T11: =Q11+R11+S11 -> 50022.321
A12: =DATE(YEAR(A11),MONTH(A11)+1,1) -> 46296 | B12: =Annahmen!C55 -> 4916.8605 | C12: =Annahmen!D55 -> 2605.46 | D12: =SUMIFS(Monatlich!$E$4:$E$63,Monatlich!$A$4:$A$63,"Ja",Monatlich!$H$4:$H$63,"Theo",Monatlich!$D$4:$D$63,"Einnahme",Monatlich!$J$4:$J$63,"<="&$A12,Monatlich!$K$4:$K$63,">="&$A12)+SUMIFS(Einmalig!$E$4:$E$43,Einmalig!$A$4:$A$43,"Ja",Einmalig!$G$4:$G$43,"Theo",Einmalig!$D$4:$D$43,"Einnahme",Einmalig!$I$4:$I$43,$A12) -> 0 | E12: =SUMIFS(Monatlich!$E$4:$E$63,Monatlich!$A$4:$A$63,"Ja",Monatlich!$H$4:$H$63,"Jule",Monatlich!$D$4:$D$63,"Einnahme",Monatlich!$J$4:$J$63,"<="&$A12,Monatlich!$K$4:$K$63,">="&$A12)+SUMIFS(Einmalig!$E$4:$E$43,Einmalig!$A$4:$A$43,"Ja",Einmalig!$G$4:$G$43,"Jule",Einmalig!$D$4:$D$43,"Einnahme",Einmalig!$I$4:$I$43,$A12) -> 0 | F12: =SUMIFS(Monatlich!$E$4:$E$63,Monatlich!$A$4:$A$63,"Ja",Monatlich!$H$4:$H$63,"Gemeinsam",Monatlich!$D$4:$D$63,"Einnahme",Monatlich!$J$4:$J$63,"<="&$A12,Monatlich!$K$4:$K$63,">="&$A12)+SUMIFS(Einmalig!$E$4:$E$43,Einmalig!$A$4:$A$43,"Ja",Einmalig!$G$4:$G$43,"Gemeinsam",Einmalig!$D$4:$D$43,"Einnahme",Einmalig!$I$4:$I$43,$A12) -> 0 | G12: =SUM(B12:F12) -> 7522.3205 | H12: =Annahmen!C17 -> 750 | I12: =Annahmen!C18 -> 750 | J12: =SUMIFS(Monatlich!$E$4:$E$63,Monatlich!$A$4:$A$63,"Ja",Monatlich!$H$4:$H$63,"Theo",Monatlich!$D$4:$D$63,"Ausgabe",Monatlich!$J$4:$J$63,"<="&$A12,Monatlich!$K$4:$K$63,">="&$A12)+SUMIFS(Einmalig!$E$4:$E$43,Einmalig!$A$4:$A$43,"Ja",Einmalig!$G$4:$G$43,"Theo",Einmalig!$D$4:$D$43,"Ausgabe",Einmalig!$I$4:$I$43,$A12) -> 0 | K12: =SUMIFS(Monatlich!$E$4:$E$63,Monatlich!$A$4:$A$63,"Ja",Monatlich!$H$4:$H$63,"Jule",Monatlich!$D$4:$D$63,"Ausgabe",Monatlich!$J$4:$J$63,"<="&$A12,Monatlich!$K$4:$K$63,">="&$A12)+SUMIFS(Einmalig!$E$4:$E$43,Einmalig!$A$4:$A$43,"Ja",Einmalig!$G$4:$G$43,"Jule",Einmalig!$D$4:$D$43,"Ausgabe",Einmalig!$I$4:$I$43,$A12) -> 0 | L12: =SUMIFS(Monatlich!$E$4:$E$63,Monatlich!$A$4:$A$63,"Ja",Monatlich!$H$4:$H$63,"Gemeinsam",Monatlich!$D$4:$D$63,"Ausgabe",Monatlich!$J$4:$J$63,"<="&$A12,Monatlich!$K$4:$K$63,">="&$A12)+SUMIFS(Einmalig!$E$4:$E$43,Einmalig!$A$4:$A$43,"Ja",Einmalig!$G$4:$G$43,"Gemeinsam",Einmalig!$D$4:$D$43,"Ausgabe",Einmalig!$I$4:$I$43,$A12) -> 2500 | M12: =SUM(H12:L12) -> 4000 | N12: =G12-M12 -> 3522.3205 | O12: =MAX(0,(Q11+B12+D12-H12-J12)-Annahmen!C19) -> 4166.8605 | P12: =MAX(0,(R11+C12+E12-I12-K12)-Annahmen!C20) -> 1855.46 | Q12: =(Q11+B12+D12-H12-J12)-O12 -> 0 | R12: =(R11+C12+E12-I12-K12)-P12 -> 0 | S12: =S11+O12+P12+F12-L12 -> 53544.641 | T12: =Q12+R12+S12 -> 53544.641
A13: =DATE(YEAR(A12),MONTH(A12)+1,1) -> 46327 | B13: =Annahmen!C55 -> 4916.8605 | C13: =Annahmen!D55 -> 2605.46 | D13: =SUMIFS(Monatlich!$E$4:$E$63,Monatlich!$A$4:$A$63,"Ja",Monatlich!$H$4:$H$63,"Theo",Monatlich!$D$4:$D$63,"Einnahme",Monatlich!$J$4:$J$63,"<="&$A13,Monatlich!$K$4:$K$63,">="&$A13)+SUMIFS(Einmalig!$E$4:$E$43,Einmalig!$A$4:$A$43,"Ja",Einmalig!$G$4:$G$43,"Theo",Einmalig!$D$4:$D$43,"Einnahme",Einmalig!$I$4:$I$43,$A13) -> 900 | E13: =SUMIFS(Monatlich!$E$4:$E$63,Monatlich!$A$4:$A$63,"Ja",Monatlich!$H$4:$H$63,"Jule",Monatlich!$D$4:$D$63,"Einnahme",Monatlich!$J$4:$J$63,"<="&$A13,Monatlich!$K$4:$K$63,">="&$A13)+SUMIFS(Einmalig!$E$4:$E$43,Einmalig!$A$4:$A$43,"Ja",Einmalig!$G$4:$G$43,"Jule",Einmalig!$D$4:$D$43,"Einnahme",Einmalig!$I$4:$I$43,$A13) -> 0 | F13: =SUMIFS(Monatlich!$E$4:$E$63,Monatlich!$A$4:$A$63,"Ja",Monatlich!$H$4:$H$63,"Gemeinsam",Monatlich!$D$4:$D$63,"Einnahme",Monatlich!$J$4:$J$63,"<="&$A13,Monatlich!$K$4:$K$63,">="&$A13)+SUMIFS(Einmalig!$E$4:$E$43,Einmalig!$A$4:$A$43,"Ja",Einmalig!$G$4:$G$43,"Gemeinsam",Einmalig!$D$4:$D$43,"Einnahme",Einmalig!$I$4:$I$43,$A13) -> 0 | G13: =SUM(B13:F13) -> 8422.3205 | H13: =Annahmen!C17 -> 750 | I13: =Annahmen!C18 -> 750 | J13: =SUMIFS(Monatlich!$E$4:$E$63,Monatlich!$A$4:$A$63,"Ja",Monatlich!$H$4:$H$63,"Theo",Monatlich!$D$4:$D$63,"Ausgabe",Monatlich!$J$4:$J$63,"<="&$A13,Monatlich!$K$4:$K$63,">="&$A13)+SUMIFS(Einmalig!$E$4:$E$43,Einmalig!$A$4:$A$43,"Ja",Einmalig!$G$4:$G$43,"Theo",Einmalig!$D$4:$D$43,"Ausgabe",Einmalig!$I$4:$I$43,$A13) -> 0 | K13: =SUMIFS(Monatlich!$E$4:$E$63,Monatlich!$A$4:$A$63,"Ja",Monatlich!$H$4:$H$63,"Jule",Monatlich!$D$4:$D$63,"Ausgabe",Monatlich!$J$4:$J$63,"<="&$A13,Monatlich!$K$4:$K$63,">="&$A13)+SUMIFS(Einmalig!$E$4:$E$43,Einmalig!$A$4:$A$43,"Ja",Einmalig!$G$4:$G$43,"Jule",Einmalig!$D$4:$D$43,"Ausgabe",Einmalig!$I$4:$I$43,$A13) -> 0 | L13: =SUMIFS(Monatlich!$E$4:$E$63,Monatlich!$A$4:$A$63,"Ja",Monatlich!$H$4:$H$63,"Gemeinsam",Monatlich!$D$4:$D$63,"Ausgabe",Monatlich!$J$4:$J$63,"<="&$A13,Monatlich!$K$4:$K$63,">="&$A13)+SUMIFS(Einmalig!$E$4:$E$43,Einmalig!$A$4:$A$43,"Ja",Einmalig!$G$4:$G$43,"Gemeinsam",Einmalig!$D$4:$D$43,"Ausgabe",Einmalig!$I$4:$I$43,$A13) -> 2500 | M13: =SUM(H13:L13) -> 4000 | N13: =G13-M13 -> 4422.3205 | O13: =MAX(0,(Q12+B13+D13-H13-J13)-Annahmen!C19) -> 5066.8605 | P13: =MAX(0,(R12+C13+E13-I13-K13)-Annahmen!C20) -> 1855.46 | Q13: =(Q12+B13+D13-H13-J13)-O13 -> 0 | R13: =(R12+C13+E13-I13-K13)-P13 -> 0 | S13: =S12+O13+P13+F13-L13 -> 57966.962 | T13: =Q13+R13+S13 -> 57966.962
A14: =DATE(YEAR(A13),MONTH(A13)+1,1) -> 46357 | B14: =Annahmen!C55 -> 4916.8605 | C14: =Annahmen!D55 -> 2605.46 | D14: =SUMIFS(Monatlich!$E$4:$E$63,Monatlich!$A$4:$A$63,"Ja",Monatlich!$H$4:$H$63,"Theo",Monatlich!$D$4:$D$63,"Einnahme",Monatlich!$J$4:$J$63,"<="&$A14,Monatlich!$K$4:$K$63,">="&$A14)+SUMIFS(Einmalig!$E$4:$E$43,Einmalig!$A$4:$A$43,"Ja",Einmalig!$G$4:$G$43,"Theo",Einmalig!$D$4:$D$43,"Einnahme",Einmalig!$I$4:$I$43,$A14) -> 0 | E14: =SUMIFS(Monatlich!$E$4:$E$63,Monatlich!$A$4:$A$63,"Ja",Monatlich!$H$4:$H$63,"Jule",Monatlich!$D$4:$D$63,"Einnahme",Monatlich!$J$4:$J$63,"<="&$A14,Monatlich!$K$4:$K$63,">="&$A14)+SUMIFS(Einmalig!$E$4:$E$43,Einmalig!$A$4:$A$43,"Ja",Einmalig!$G$4:$G$43,"Jule",Einmalig!$D$4:$D$43,"Einnahme",Einmalig!$I$4:$I$43,$A14) -> 0 | F14: =SUMIFS(Monatlich!$E$4:$E$63,Monatlich!$A$4:$A$63,"Ja",Monatlich!$H$4:$H$63,"Gemeinsam",Monatlich!$D$4:$D$63,"Einnahme",Monatlich!$J$4:$J$63,"<="&$A14,Monatlich!$K$4:$K$63,">="&$A14)+SUMIFS(Einmalig!$E$4:$E$43,Einmalig!$A$4:$A$43,"Ja",Einmalig!$G$4:$G$43,"Gemeinsam",Einmalig!$D$4:$D$43,"Einnahme",Einmalig!$I$4:$I$43,$A14) -> 0 | G14: =SUM(B14:F14) -> 7522.3205 | H14: =Annahmen!C17 -> 750 | I14: =Annahmen!C18 -> 750 | J14: =SUMIFS(Monatlich!$E$4:$E$63,Monatlich!$A$4:$A$63,"Ja",Monatlich!$H$4:$H$63,"Theo",Monatlich!$D$4:$D$63,"Ausgabe",Monatlich!$J$4:$J$63,"<="&$A14,Monatlich!$K$4:$K$63,">="&$A14)+SUMIFS(Einmalig!$E$4:$E$43,Einmalig!$A$4:$A$43,"Ja",Einmalig!$G$4:$G$43,"Theo",Einmalig!$D$4:$D$43,"Ausgabe",Einmalig!$I$4:$I$43,$A14) -> 0 | K14: =SUMIFS(Monatlich!$E$4:$E$63,Monatlich!$A$4:$A$63,"Ja",Monatlich!$H$4:$H$63,"Jule",Monatlich!$D$4:$D$63,"Ausgabe",Monatlich!$J$4:$J$63,"<="&$A14,Monatlich!$K$4:$K$63,">="&$A14)+SUMIFS(Einmalig!$E$4:$E$43,Einmalig!$A$4:$A$43,"Ja",Einmalig!$G$4:$G$43,"Jule",Einmalig!$D$4:$D$43,"Ausgabe",Einmalig!$I$4:$I$43,$A14) -> 0 | L14: =SUMIFS(Monatlich!$E$4:$E$63,Monatlich!$A$4:$A$63,"Ja",Monatlich!$H$4:$H$63,"Gemeinsam",Monatlich!$D$4:$D$63,"Ausgabe",Monatlich!$J$4:$J$63,"<="&$A14,Monatlich!$K$4:$K$63,">="&$A14)+SUMIFS(Einmalig!$E$4:$E$43,Einmalig!$A$4:$A$43,"Ja",Einmalig!$G$4:$G$43,"Gemeinsam",Einmalig!$D$4:$D$43,"Ausgabe",Einmalig!$I$4:$I$43,$A14) -> 2500 | M14: =SUM(H14:L14) -> 4000 | N14: =G14-M14 -> 3522.3205 | O14: =MAX(0,(Q13+B14+D14-H14-J14)-Annahmen!C19) -> 4166.8605 | P14: =MAX(0,(R13+C14+E14-I14-K14)-Annahmen!C20) -> 1855.46 | Q14: =(Q13+B14+D14-H14-J14)-O14 -> 0 | R14: =(R13+C14+E14-I14-K14)-P14 -> 0 | S14: =S13+O14+P14+F14-L14 -> 61489.282 | T14: =Q14+R14+S14 -> 61489.282
A15: =DATE(YEAR(A14),MONTH(A14)+1,1) -> 46388 | B15: =Annahmen!C55 -> 4916.8605 | C15: =Annahmen!D55 -> 2605.46 | D15: =SUMIFS(Monatlich!$E$4:$E$63,Monatlich!$A$4:$A$63,"Ja",Monatlich!$H$4:$H$63,"Theo",Monatlich!$D$4:$D$63,"Einnahme",Monatlich!$J$4:$J$63,"<="&$A15,Monatlich!$K$4:$K$63,">="&$A15)+SUMIFS(Einmalig!$E$4:$E$43,Einmalig!$A$4:$A$43,"Ja",Einmalig!$G$4:$G$43,"Theo",Einmalig!$D$4:$D$43,"Einnahme",Einmalig!$I$4:$I$43,$A15) -> 0 | E15: =SUMIFS(Monatlich!$E$4:$E$63,Monatlich!$A$4:$A$63,"Ja",Monatlich!$H$4:$H$63,"Jule",Monatlich!$D$4:$D$63,"Einnahme",Monatlich!$J$4:$J$63,"<="&$A15,Monatlich!$K$4:$K$63,">="&$A15)+SUMIFS(Einmalig!$E$4:$E$43,Einmalig!$A$4:$A$43,"Ja",Einmalig!$G$4:$G$43,"Jule",Einmalig!$D$4:$D$43,"Einnahme",Einmalig!$I$4:$I$43,$A15) -> 0 | F15: =SUMIFS(Monatlich!$E$4:$E$63,Monatlich!$A$4:$A$63,"Ja",Monatlich!$H$4:$H$63,"Gemeinsam",Monatlich!$D$4:$D$63,"Einnahme",Monatlich!$J$4:$J$63,"<="&$A15,Monatlich!$K$4:$K$63,">="&$A15)+SUMIFS(Einmalig!$E$4:$E$43,Einmalig!$A$4:$A$43,"Ja",Einmalig!$G$4:$G$43,"Gemeinsam",Einmalig!$D$4:$D$43,"Einnahme",Einmalig!$I$4:$I$43,$A15) -> 0 | G15: =SUM(B15:F15) -> 7522.3205 | H15: =Annahmen!C17 -> 750 | I15: =Annahmen!C18 -> 750 | J15: =SUMIFS(Monatlich!$E$4:$E$63,Monatlich!$A$4:$A$63,"Ja",Monatlich!$H$4:$H$63,"Theo",Monatlich!$D$4:$D$63,"Ausgabe",Monatlich!$J$4:$J$63,"<="&$A15,Monatlich!$K$4:$K$63,">="&$A15)+SUMIFS(Einmalig!$E$4:$E$43,Einmalig!$A$4:$A$43,"Ja",Einmalig!$G$4:$G$43,"Theo",Einmalig!$D$4:$D$43,"Ausgabe",Einmalig!$I$4:$I$43,$A15) -> 0 | K15: =SUMIFS(Monatlich!$E$4:$E$63,Monatlich!$A$4:$A$63,"Ja",Monatlich!$H$4:$H$63,"Jule",Monatlich!$D$4:$D$63,"Ausgabe",Monatlich!$J$4:$J$63,"<="&$A15,Monatlich!$K$4:$K$63,">="&$A15)+SUMIFS(Einmalig!$E$4:$E$43,Einmalig!$A$4:$A$43,"Ja",Einmalig!$G$4:$G$43,"Jule",Einmalig!$D$4:$D$43,"Ausgabe",Einmalig!$I$4:$I$43,$A15) -> 0 | L15: =SUMIFS(Monatlich!$E$4:$E$63,Monatlich!$A$4:$A$63,"Ja",Monatlich!$H$4:$H$63,"Gemeinsam",Monatlich!$D$4:$D$63,"Ausgabe",Monatlich!$J$4:$J$63,"<="&$A15,Monatlich!$K$4:$K$63,">="&$A15)+SUMIFS(Einmalig!$E$4:$E$43,Einmalig!$A$4:$A$43,"Ja",Einmalig!$G$4:$G$43,"Gemeinsam",Einmalig!$D$4:$D$43,"Ausgabe",Einmalig!$I$4:$I$43,$A15) -> 2500 | M15: =SUM(H15:L15) -> 4000 | N15: =G15-M15 -> 3522.3205 | O15: =MAX(0,(Q14+B15+D15-H15-J15)-Annahmen!C19) -> 4166.8605 | P15: =MAX(0,(R14+C15+E15-I15-K15)-Annahmen!C20) -> 1855.46 | Q15: =(Q14+B15+D15-H15-J15)-O15 -> 0 | R15: =(R14+C15+E15-I15-K15)-P15 -> 0 | S15: =S14+O15+P15+F15-L15 -> 65011.603 | T15: =Q15+R15+S15 -> 65011.603
A16: =DATE(YEAR(A15),MONTH(A15)+1,1) -> 46419 | B16: =Annahmen!C55 -> 4916.8605 | C16: =Annahmen!D55 -> 2605.46 | D16: =SUMIFS(Monatlich!$E$4:$E$63,Monatlich!$A$4:$A$63,"Ja",Monatlich!$H$4:$H$63,"Theo",Monatlich!$D$4:$D$63,"Einnahme",Monatlich!$J$4:$J$63,"<="&$A16,Monatlich!$K$4:$K$63,">="&$A16)+SUMIFS(Einmalig!$E$4:$E$43,Einmalig!$A$4:$A$43,"Ja",Einmalig!$G$4:$G$43,"Theo",Einmalig!$D$4:$D$43,"Einnahme",Einmalig!$I$4:$I$43,$A16) -> 0 | E16: =SUMIFS(Monatlich!$E$4:$E$63,Monatlich!$A$4:$A$63,"Ja",Monatlich!$H$4:$H$63,"Jule",Monatlich!$D$4:$D$63,"Einnahme",Monatlich!$J$4:$J$63,"<="&$A16,Monatlich!$K$4:$K$63,">="&$A16)+SUMIFS(Einmalig!$E$4:$E$43,Einmalig!$A$4:$A$43,"Ja",Einmalig!$G$4:$G$43,"Jule",Einmalig!$D$4:$D$43,"Einnahme",Einmalig!$I$4:$I$43,$A16) -> 0 | F16: =SUMIFS(Monatlich!$E$4:$E$63,Monatlich!$A$4:$A$63,"Ja",Monatlich!$H$4:$H$63,"Gemeinsam",Monatlich!$D$4:$D$63,"Einnahme",Monatlich!$J$4:$J$63,"<="&$A16,Monatlich!$K$4:$K$63,">="&$A16)+SUMIFS(Einmalig!$E$4:$E$43,Einmalig!$A$4:$A$43,"Ja",Einmalig!$G$4:$G$43,"Gemeinsam",Einmalig!$D$4:$D$43,"Einnahme",Einmalig!$I$4:$I$43,$A16) -> 0 | G16: =SUM(B16:F16) -> 7522.3205 | H16: =Annahmen!C17 -> 750 | I16: =Annahmen!C18 -> 750 | J16: =SUMIFS(Monatlich!$E$4:$E$63,Monatlich!$A$4:$A$63,"Ja",Monatlich!$H$4:$H$63,"Theo",Monatlich!$D$4:$D$63,"Ausgabe",Monatlich!$J$4:$J$63,"<="&$A16,Monatlich!$K$4:$K$63,">="&$A16)+SUMIFS(Einmalig!$E$4:$E$43,Einmalig!$A$4:$A$43,"Ja",Einmalig!$G$4:$G$43,"Theo",Einmalig!$D$4:$D$43,"Ausgabe",Einmalig!$I$4:$I$43,$A16) -> 0 | K16: =SUMIFS(Monatlich!$E$4:$E$63,Monatlich!$A$4:$A$63,"Ja",Monatlich!$H$4:$H$63,"Jule",Monatlich!$D$4:$D$63,"Ausgabe",Monatlich!$J$4:$J$63,"<="&$A16,Monatlich!$K$4:$K$63,">="&$A16)+SUMIFS(Einmalig!$E$4:$E$43,Einmalig!$A$4:$A$43,"Ja",Einmalig!$G$4:$G$43,"Jule",Einmalig!$D$4:$D$43,"Ausgabe",Einmalig!$I$4:$I$43,$A16) -> 0 | L16: =SUMIFS(Monatlich!$E$4:$E$63,Monatlich!$A$4:$A$63,"Ja",Monatlich!$H$4:$H$63,"Gemeinsam",Monatlich!$D$4:$D$63,"Ausgabe",Monatlich!$J$4:$J$63,"<="&$A16,Monatlich!$K$4:$K$63,">="&$A16)+SUMIFS(Einmalig!$E$4:$E$43,Einmalig!$A$4:$A$43,"Ja",Einmalig!$G$4:$G$43,"Gemeinsam",Einmalig!$D$4:$D$43,"Ausgabe",Einmalig!$I$4:$I$43,$A16) -> 2500 | M16: =SUM(H16:L16) -> 4000 | N16: =G16-M16 -> 3522.3205 | O16: =MAX(0,(Q15+B16+D16-H16-J16)-Annahmen!C19) -> 4166.8605 | P16: =MAX(0,(R15+C16+E16-I16-K16)-Annahmen!C20) -> 1855.46 | Q16: =(Q15+B16+D16-H16-J16)-O16 -> 0 | R16: =(R15+C16+E16-I16-K16)-P16 -> 0 | S16: =S15+O16+P16+F16-L16 -> 68533.923 | T16: =Q16+R16+S16 -> 68533.923
A17: =DATE(YEAR(A16),MONTH(A16)+1,1) -> 46447 | B17: =Annahmen!C55 -> 4916.8605 | C17: =Annahmen!D55 -> 2605.46 | D17: =SUMIFS(Monatlich!$E$4:$E$63,Monatlich!$A$4:$A$63,"Ja",Monatlich!$H$4:$H$63,"Theo",Monatlich!$D$4:$D$63,"Einnahme",Monatlich!$J$4:$J$63,"<="&$A17,Monatlich!$K$4:$K$63,">="&$A17)+SUMIFS(Einmalig!$E$4:$E$43,Einmalig!$A$4:$A$43,"Ja",Einmalig!$G$4:$G$43,"Theo",Einmalig!$D$4:$D$43,"Einnahme",Einmalig!$I$4:$I$43,$A17) -> 0 | E17: =SUMIFS(Monatlich!$E$4:$E$63,Monatlich!$A$4:$A$63,"Ja",Monatlich!$H$4:$H$63,"Jule",Monatlich!$D$4:$D$63,"Einnahme",Monatlich!$J$4:$J$63,"<="&$A17,Monatlich!$K$4:$K$63,">="&$A17)+SUMIFS(Einmalig!$E$4:$E$43,Einmalig!$A$4:$A$43,"Ja",Einmalig!$G$4:$G$43,"Jule",Einmalig!$D$4:$D$43,"Einnahme",Einmalig!$I$4:$I$43,$A17) -> 0 | F17: =SUMIFS(Monatlich!$E$4:$E$63,Monatlich!$A$4:$A$63,"Ja",Monatlich!$H$4:$H$63,"Gemeinsam",Monatlich!$D$4:$D$63,"Einnahme",Monatlich!$J$4:$J$63,"<="&$A17,Monatlich!$K$4:$K$63,">="&$A17)+SUMIFS(Einmalig!$E$4:$E$43,Einmalig!$A$4:$A$43,"Ja",Einmalig!$G$4:$G$43,"Gemeinsam",Einmalig!$D$4:$D$43,"Einnahme",Einmalig!$I$4:$I$43,$A17) -> 0 | G17: =SUM(B17:F17) -> 7522.3205 | H17: =Annahmen!C17 -> 750 | I17: =Annahmen!C18 -> 750 | J17: =SUMIFS(Monatlich!$E$4:$E$63,Monatlich!$A$4:$A$63,"Ja",Monatlich!$H$4:$H$63,"Theo",Monatlich!$D$4:$D$63,"Ausgabe",Monatlich!$J$4:$J$63,"<="&$A17,Monatlich!$K$4:$K$63,">="&$A17)+SUMIFS(Einmalig!$E$4:$E$43,Einmalig!$A$4:$A$43,"Ja",Einmalig!$G$4:$G$43,"Theo",Einmalig!$D$4:$D$43,"Ausgabe",Einmalig!$I$4:$I$43,$A17) -> 0 | K17: =SUMIFS(Monatlich!$E$4:$E$63,Monatlich!$A$4:$A$63,"Ja",Monatlich!$H$4:$H$63,"Jule",Monatlich!$D$4:$D$63,"Ausgabe",Monatlich!$J$4:$J$63,"<="&$A17,Monatlich!$K$4:$K$63,">="&$A17)+SUMIFS(Einmalig!$E$4:$E$43,Einmalig!$A$4:$A$43,"Ja",Einmalig!$G$4:$G$43,"Jule",Einmalig!$D$4:$D$43,"Ausgabe",Einmalig!$I$4:$I$43,$A17) -> 0 | L17: =SUMIFS(Monatlich!$E$4:$E$63,Monatlich!$A$4:$A$63,"Ja",Monatlich!$H$4:$H$63,"Gemeinsam",Monatlich!$D$4:$D$63,"Ausgabe",Monatlich!$J$4:$J$63,"<="&$A17,Monatlich!$K$4:$K$63,">="&$A17)+SUMIFS(Einmalig!$E$4:$E$43,Einmalig!$A$4:$A$43,"Ja",Einmalig!$G$4:$G$43,"Gemeinsam",Einmalig!$D$4:$D$43,"Ausgabe",Einmalig!$I$4:$I$43,$A17) -> 2500 | M17: =SUM(H17:L17) -> 4000 | N17: =G17-M17 -> 3522.3205 | O17: =MAX(0,(Q16+B17+D17-H17-J17)-Annahmen!C19) -> 4166.8605 | P17: =MAX(0,(R16+C17+E17-I17-K17)-Annahmen!C20) -> 1855.46 | Q17: =(Q16+B17+D17-H17-J17)-O17 -> 0 | R17: =(R16+C17+E17-I17-K17)-P17 -> 0 | S17: =S16+O17+P17+F17-L17 -> 72056.244 | T17: =Q17+R17+S17 -> 72056.244
A18: =DATE(YEAR(A17),MONTH(A17)+1,1) -> 46478 | B18: =Annahmen!C55 -> 4916.8605 | C18: =Annahmen!D55 -> 2605.46 | D18: =SUMIFS(Monatlich!$E$4:$E$63,Monatlich!$A$4:$A$63,"Ja",Monatlich!$H$4:$H$63,"Theo",Monatlich!$D$4:$D$63,"Einnahme",Monatlich!$J$4:$J$63,"<="&$A18,Monatlich!$K$4:$K$63,">="&$A18)+SUMIFS(Einmalig!$E$4:$E$43,Einmalig!$A$4:$A$43,"Ja",Einmalig!$G$4:$G$43,"Theo",Einmalig!$D$4:$D$43,"Einnahme",Einmalig!$I$4:$I$43,$A18) -> 0 | E18: =SUMIFS(Monatlich!$E$4:$E$63,Monatlich!$A$4:$A$63,"Ja",Monatlich!$H$4:$H$63,"Jule",Monatlich!$D$4:$D$63,"Einnahme",Monatlich!$J$4:$J$63,"<="&$A18,Monatlich!$K$4:$K$63,">="&$A18)+SUMIFS(Einmalig!$E$4:$E$43,Einmalig!$A$4:$A$43,"Ja",Einmalig!$G$4:$G$43,"Jule",Einmalig!$D$4:$D$43,"Einnahme",Einmalig!$I$4:$I$43,$A18) -> 0 | F18: =SUMIFS(Monatlich!$E$4:$E$63,Monatlich!$A$4:$A$63,"Ja",Monatlich!$H$4:$H$63,"Gemeinsam",Monatlich!$D$4:$D$63,"Einnahme",Monatlich!$J$4:$J$63,"<="&$A18,Monatlich!$K$4:$K$63,">="&$A18)+SUMIFS(Einmalig!$E$4:$E$43,Einmalig!$A$4:$A$43,"Ja",Einmalig!$G$4:$G$43,"Gemeinsam",Einmalig!$D$4:$D$43,"Einnahme",Einmalig!$I$4:$I$43,$A18) -> 0 | G18: =SUM(B18:F18) -> 7522.3205 | H18: =Annahmen!C17 -> 750 | I18: =Annahmen!C18 -> 750 | J18: =SUMIFS(Monatlich!$E$4:$E$63,Monatlich!$A$4:$A$63,"Ja",Monatlich!$H$4:$H$63,"Theo",Monatlich!$D$4:$D$63,"Ausgabe",Monatlich!$J$4:$J$63,"<="&$A18,Monatlich!$K$4:$K$63,">="&$A18)+SUMIFS(Einmalig!$E$4:$E$43,Einmalig!$A$4:$A$43,"Ja",Einmalig!$G$4:$G$43,"Theo",Einmalig!$D$4:$D$43,"Ausgabe",Einmalig!$I$4:$I$43,$A18) -> 0 | K18: =SUMIFS(Monatlich!$E$4:$E$63,Monatlich!$A$4:$A$63,"Ja",Monatlich!$H$4:$H$63,"Jule",Monatlich!$D$4:$D$63,"Ausgabe",Monatlich!$J$4:$J$63,"<="&$A18,Monatlich!$K$4:$K$63,">="&$A18)+SUMIFS(Einmalig!$E$4:$E$43,Einmalig!$A$4:$A$43,"Ja",Einmalig!$G$4:$G$43,"Jule",Einmalig!$D$4:$D$43,"Ausgabe",Einmalig!$I$4:$I$43,$A18) -> 0 | L18: =SUMIFS(Monatlich!$E$4:$E$63,Monatlich!$A$4:$A$63,"Ja",Monatlich!$H$4:$H$63,"Gemeinsam",Monatlich!$D$4:$D$63,"Ausgabe",Monatlich!$J$4:$J$63,"<="&$A18,Monatlich!$K$4:$K$63,">="&$A18)+SUMIFS(Einmalig!$E$4:$E$43,Einmalig!$A$4:$A$43,"Ja",Einmalig!$G$4:$G$43,"Gemeinsam",Einmalig!$D$4:$D$43,"Ausgabe",Einmalig!$I$4:$I$43,$A18) -> 2500 | M18: =SUM(H18:L18) -> 4000 | N18: =G18-M18 -> 3522.3205 | O18: =MAX(0,(Q17+B18+D18-H18-J18)-Annahmen!C19) -> 4166.8605 | P18: =MAX(0,(R17+C18+E18-I18-K18)-Annahmen!C20) -> 1855.46 | Q18: =(Q17+B18+D18-H18-J18)-O18 -> 0 | R18: =(R17+C18+E18-I18-K18)-P18 -> 0 | S18: =S17+O18+P18+F18-L18 -> 75578.564 | T18: =Q18+R18+S18 -> 75578.564
A19: =DATE(YEAR(A18),MONTH(A18)+1,1) -> 46508 | B19: =Annahmen!C55 -> 4916.8605 | C19: =Annahmen!D55 -> 2605.46 | D19: =SUMIFS(Monatlich!$E$4:$E$63,Monatlich!$A$4:$A$63,"Ja",Monatlich!$H$4:$H$63,"Theo",Monatlich!$D$4:$D$63,"Einnahme",Monatlich!$J$4:$J$63,"<="&$A19,Monatlich!$K$4:$K$63,">="&$A19)+SUMIFS(Einmalig!$E$4:$E$43,Einmalig!$A$4:$A$43,"Ja",Einmalig!$G$4:$G$43,"Theo",Einmalig!$D$4:$D$43,"Einnahme",Einmalig!$I$4:$I$43,$A19) -> 0 | E19: =SUMIFS(Monatlich!$E$4:$E$63,Monatlich!$A$4:$A$63,"Ja",Monatlich!$H$4:$H$63,"Jule",Monatlich!$D$4:$D$63,"Einnahme",Monatlich!$J$4:$J$63,"<="&$A19,Monatlich!$K$4:$K$63,">="&$A19)+SUMIFS(Einmalig!$E$4:$E$43,Einmalig!$A$4:$A$43,"Ja",Einmalig!$G$4:$G$43,"Jule",Einmalig!$D$4:$D$43,"Einnahme",Einmalig!$I$4:$I$43,$A19) -> 0 | F19: =SUMIFS(Monatlich!$E$4:$E$63,Monatlich!$A$4:$A$63,"Ja",Monatlich!$H$4:$H$63,"Gemeinsam",Monatlich!$D$4:$D$63,"Einnahme",Monatlich!$J$4:$J$63,"<="&$A19,Monatlich!$K$4:$K$63,">="&$A19)+SUMIFS(Einmalig!$E$4:$E$43,Einmalig!$A$4:$A$43,"Ja",Einmalig!$G$4:$G$43,"Gemeinsam",Einmalig!$D$4:$D$43,"Einnahme",Einmalig!$I$4:$I$43,$A19) -> 0 | G19: =SUM(B19:F19) -> 7522.3205 | H19: =Annahmen!C17 -> 750 | I19: =Annahmen!C18 -> 750 | J19: =SUMIFS(Monatlich!$E$4:$E$63,Monatlich!$A$4:$A$63,"Ja",Monatlich!$H$4:$H$63,"Theo",Monatlich!$D$4:$D$63,"Ausgabe",Monatlich!$J$4:$J$63,"<="&$A19,Monatlich!$K$4:$K$63,">="&$A19)+SUMIFS(Einmalig!$E$4:$E$43,Einmalig!$A$4:$A$43,"Ja",Einmalig!$G$4:$G$43,"Theo",Einmalig!$D$4:$D$43,"Ausgabe",Einmalig!$I$4:$I$43,$A19) -> 0 | K19: =SUMIFS(Monatlich!$E$4:$E$63,Monatlich!$A$4:$A$63,"Ja",Monatlich!$H$4:$H$63,"Jule",Monatlich!$D$4:$D$63,"Ausgabe",Monatlich!$J$4:$J$63,"<="&$A19,Monatlich!$K$4:$K$63,">="&$A19)+SUMIFS(Einmalig!$E$4:$E$43,Einmalig!$A$4:$A$43,"Ja",Einmalig!$G$4:$G$43,"Jule",Einmalig!$D$4:$D$43,"Ausgabe",Einmalig!$I$4:$I$43,$A19) -> 0 | L19: =SUMIFS(Monatlich!$E$4:$E$63,Monatlich!$A$4:$A$63,"Ja",Monatlich!$H$4:$H$63,"Gemeinsam",Monatlich!$D$4:$D$63,"Ausgabe",Monatlich!$J$4:$J$63,"<="&$A19,Monatlich!$K$4:$K$63,">="&$A19)+SUMIFS(Einmalig!$E$4:$E$43,Einmalig!$A$4:$A$43,"Ja",Einmalig!$G$4:$G$43,"Gemeinsam",Einmalig!$D$4:$D$43,"Ausgabe",Einmalig!$I$4:$I$43,$A19) -> 2500 | M19: =SUM(H19:L19) -> 4000 | N19: =G19-M19 -> 3522.3205 | O19: =MAX(0,(Q18+B19+D19-H19-J19)-Annahmen!C19) -> 4166.8605 | P19: =MAX(0,(R18+C19+E19-I19-K19)-Annahmen!C20) -> 1855.46 | Q19: =(Q18+B19+D19-H19-J19)-O19 -> 0 | R19: =(R18+C19+E19-I19-K19)-P19 -> 0 | S19: =S18+O19+P19+F19-L19 -> 79100.885 | T19: =Q19+R19+S19 -> 79100.885
A20: =DATE(YEAR(A19),MONTH(A19)+1,1) -> 46539 | B20: =Annahmen!C55 -> 4916.8605 | C20: =Annahmen!D55 -> 2605.46 | D20: =SUMIFS(Monatlich!$E$4:$E$63,Monatlich!$A$4:$A$63,"Ja",Monatlich!$H$4:$H$63,"Theo",Monatlich!$D$4:$D$63,"Einnahme",Monatlich!$J$4:$J$63,"<="&$A20,Monatlich!$K$4:$K$63,">="&$A20)+SUMIFS(Einmalig!$E$4:$E$43,Einmalig!$A$4:$A$43,"Ja",Einmalig!$G$4:$G$43,"Theo",Einmalig!$D$4:$D$43,"Einnahme",Einmalig!$I$4:$I$43,$A20) -> 0 | E20: =SUMIFS(Monatlich!$E$4:$E$63,Monatlich!$A$4:$A$63,"Ja",Monatlich!$H$4:$H$63,"Jule",Monatlich!$D$4:$D$63,"Einnahme",Monatlich!$J$4:$J$63,"<="&$A20,Monatlich!$K$4:$K$63,">="&$A20)+SUMIFS(Einmalig!$E$4:$E$43,Einmalig!$A$4:$A$43,"Ja",Einmalig!$G$4:$G$43,"Jule",Einmalig!$D$4:$D$43,"Einnahme",Einmalig!$I$4:$I$43,$A20) -> 0 | F20: =SUMIFS(Monatlich!$E$4:$E$63,Monatlich!$A$4:$A$63,"Ja",Monatlich!$H$4:$H$63,"Gemeinsam",Monatlich!$D$4:$D$63,"Einnahme",Monatlich!$J$4:$J$63,"<="&$A20,Monatlich!$K$4:$K$63,">="&$A20)+SUMIFS(Einmalig!$E$4:$E$43,Einmalig!$A$4:$A$43,"Ja",Einmalig!$G$4:$G$43,"Gemeinsam",Einmalig!$D$4:$D$43,"Einnahme",Einmalig!$I$4:$I$43,$A20) -> 0 | G20: =SUM(B20:F20) -> 7522.3205 | H20: =Annahmen!C17 -> 750 | I20: =Annahmen!C18 -> 750 | J20: =SUMIFS(Monatlich!$E$4:$E$63,Monatlich!$A$4:$A$63,"Ja",Monatlich!$H$4:$H$63,"Theo",Monatlich!$D$4:$D$63,"Ausgabe",Monatlich!$J$4:$J$63,"<="&$A20,Monatlich!$K$4:$K$63,">="&$A20)+SUMIFS(Einmalig!$E$4:$E$43,Einmalig!$A$4:$A$43,"Ja",Einmalig!$G$4:$G$43,"Theo",Einmalig!$D$4:$D$43,"Ausgabe",Einmalig!$I$4:$I$43,$A20) -> 0 | K20: =SUMIFS(Monatlich!$E$4:$E$63,Monatlich!$A$4:$A$63,"Ja",Monatlich!$H$4:$H$63,"Jule",Monatlich!$D$4:$D$63,"Ausgabe",Monatlich!$J$4:$J$63,"<="&$A20,Monatlich!$K$4:$K$63,">="&$A20)+SUMIFS(Einmalig!$E$4:$E$43,Einmalig!$A$4:$A$43,"Ja",Einmalig!$G$4:$G$43,"Jule",Einmalig!$D$4:$D$43,"Ausgabe",Einmalig!$I$4:$I$43,$A20) -> 0 | L20: =SUMIFS(Monatlich!$E$4:$E$63,Monatlich!$A$4:$A$63,"Ja",Monatlich!$H$4:$H$63,"Gemeinsam",Monatlich!$D$4:$D$63,"Ausgabe",Monatlich!$J$4:$J$63,"<="&$A20,Monatlich!$K$4:$K$63,">="&$A20)+SUMIFS(Einmalig!$E$4:$E$43,Einmalig!$A$4:$A$43,"Ja",Einmalig!$G$4:$G$43,"Gemeinsam",Einmalig!$D$4:$D$43,"Ausgabe",Einmalig!$I$4:$I$43,$A20) -> 2500 | M20: =SUM(H20:L20) -> 4000 | N20: =G20-M20 -> 3522.3205 | O20: =MAX(0,(Q19+B20+D20-H20-J20)-Annahmen!C19) -> 4166.8605 | P20: =MAX(0,(R19+C20+E20-I20-K20)-Annahmen!C20) -> 1855.46 | Q20: =(Q19+B20+D20-H20-J20)-O20 -> 0 | R20: =(R19+C20+E20-I20-K20)-P20 -> 0 | S20: =S19+O20+P20+F20-L20 -> 82623.205 | T20: =Q20+R20+S20 -> 82623.205
A21: =DATE(YEAR(A20),MONTH(A20)+1,1) -> 46569 | B21: =Annahmen!C55 -> 4916.8605 | C21: =Annahmen!D55 -> 2605.46 | D21: =SUMIFS(Monatlich!$E$4:$E$63,Monatlich!$A$4:$A$63,"Ja",Monatlich!$H$4:$H$63,"Theo",Monatlich!$D$4:$D$63,"Einnahme",Monatlich!$J$4:$J$63,"<="&$A21,Monatlich!$K$4:$K$63,">="&$A21)+SUMIFS(Einmalig!$E$4:$E$43,Einmalig!$A$4:$A$43,"Ja",Einmalig!$G$4:$G$43,"Theo",Einmalig!$D$4:$D$43,"Einnahme",Einmalig!$I$4:$I$43,$A21) -> 0 | E21: =SUMIFS(Monatlich!$E$4:$E$63,Monatlich!$A$4:$A$63,"Ja",Monatlich!$H$4:$H$63,"Jule",Monatlich!$D$4:$D$63,"Einnahme",Monatlich!$J$4:$J$63,"<="&$A21,Monatlich!$K$4:$K$63,">="&$A21)+SUMIFS(Einmalig!$E$4:$E$43,Einmalig!$A$4:$A$43,"Ja",Einmalig!$G$4:$G$43,"Jule",Einmalig!$D$4:$D$43,"Einnahme",Einmalig!$I$4:$I$43,$A21) -> 0 | F21: =SUMIFS(Monatlich!$E$4:$E$63,Monatlich!$A$4:$A$63,"Ja",Monatlich!$H$4:$H$63,"Gemeinsam",Monatlich!$D$4:$D$63,"Einnahme",Monatlich!$J$4:$J$63,"<="&$A21,Monatlich!$K$4:$K$63,">="&$A21)+SUMIFS(Einmalig!$E$4:$E$43,Einmalig!$A$4:$A$43,"Ja",Einmalig!$G$4:$G$43,"Gemeinsam",Einmalig!$D$4:$D$43,"Einnahme",Einmalig!$I$4:$I$43,$A21) -> 0 | G21: =SUM(B21:F21) -> 7522.3205 | H21: =Annahmen!C17 -> 750 | I21: =Annahmen!C18 -> 750 | J21: =SUMIFS(Monatlich!$E$4:$E$63,Monatlich!$A$4:$A$63,"Ja",Monatlich!$H$4:$H$63,"Theo",Monatlich!$D$4:$D$63,"Ausgabe",Monatlich!$J$4:$J$63,"<="&$A21,Monatlich!$K$4:$K$63,">="&$A21)+SUMIFS(Einmalig!$E$4:$E$43,Einmalig!$A$4:$A$43,"Ja",Einmalig!$G$4:$G$43,"Theo",Einmalig!$D$4:$D$43,"Ausgabe",Einmalig!$I$4:$I$43,$A21) -> 0 | K21: =SUMIFS(Monatlich!$E$4:$E$63,Monatlich!$A$4:$A$63,"Ja",Monatlich!$H$4:$H$63,"Jule",Monatlich!$D$4:$D$63,"Ausgabe",Monatlich!$J$4:$J$63,"<="&$A21,Monatlich!$K$4:$K$63,">="&$A21)+SUMIFS(Einmalig!$E$4:$E$43,Einmalig!$A$4:$A$43,"Ja",Einmalig!$G$4:$G$43,"Jule",Einmalig!$D$4:$D$43,"Ausgabe",Einmalig!$I$4:$I$43,$A21) -> 0 | L21: =SUMIFS(Monatlich!$E$4:$E$63,Monatlich!$A$4:$A$63,"Ja",Monatlich!$H$4:$H$63,"Gemeinsam",Monatlich!$D$4:$D$63,"Ausgabe",Monatlich!$J$4:$J$63,"<="&$A21,Monatlich!$K$4:$K$63,">="&$A21)+SUMIFS(Einmalig!$E$4:$E$43,Einmalig!$A$4:$A$43,"Ja",Einmalig!$G$4:$G$43,"Gemeinsam",Einmalig!$D$4:$D$43,"Ausgabe",Einmalig!$I$4:$I$43,$A21) -> 2500 | M21: =SUM(H21:L21) -> 4000 | N21: =G21-M21 -> 3522.3205 | O21: =MAX(0,(Q20+B21+D21-H21-J21)-Annahmen!C19) -> 4166.8605 | P21: =MAX(0,(R20+C21+E21-I21-K21)-Annahmen!C20) -> 1855.46 | Q21: =(Q20+B21+D21-H21-J21)-O21 -> 0 | R21: =(R20+C21+E21-I21-K21)-P21 -> 0 | S21: =S20+O21+P21+F21-L21 -> 86145.526 | T21: =Q21+R21+S21 -> 86145.526
A22: =DATE(YEAR(A21),MONTH(A21)+1,1) -> 46600 | B22: =Annahmen!C55 -> 4916.8605 | C22: =Annahmen!D55 -> 2605.46 | D22: =SUMIFS(Monatlich!$E$4:$E$63,Monatlich!$A$4:$A$63,"Ja",Monatlich!$H$4:$H$63,"Theo",Monatlich!$D$4:$D$63,"Einnahme",Monatlich!$J$4:$J$63,"<="&$A22,Monatlich!$K$4:$K$63,">="&$A22)+SUMIFS(Einmalig!$E$4:$E$43,Einmalig!$A$4:$A$43,"Ja",Einmalig!$G$4:$G$43,"Theo",Einmalig!$D$4:$D$43,"Einnahme",Einmalig!$I$4:$I$43,$A22) -> 0 | E22: =SUMIFS(Monatlich!$E$4:$E$63,Monatlich!$A$4:$A$63,"Ja",Monatlich!$H$4:$H$63,"Jule",Monatlich!$D$4:$D$63,"Einnahme",Monatlich!$J$4:$J$63,"<="&$A22,Monatlich!$K$4:$K$63,">="&$A22)+SUMIFS(Einmalig!$E$4:$E$43,Einmalig!$A$4:$A$43,"Ja",Einmalig!$G$4:$G$43,"Jule",Einmalig!$D$4:$D$43,"Einnahme",Einmalig!$I$4:$I$43,$A22) -> 0 | F22: =SUMIFS(Monatlich!$E$4:$E$63,Monatlich!$A$4:$A$63,"Ja",Monatlich!$H$4:$H$63,"Gemeinsam",Monatlich!$D$4:$D$63,"Einnahme",Monatlich!$J$4:$J$63,"<="&$A22,Monatlich!$K$4:$K$63,">="&$A22)+SUMIFS(Einmalig!$E$4:$E$43,Einmalig!$A$4:$A$43,"Ja",Einmalig!$G$4:$G$43,"Gemeinsam",Einmalig!$D$4:$D$43,"Einnahme",Einmalig!$I$4:$I$43,$A22) -> 0 | G22: =SUM(B22:F22) -> 7522.3205 | H22: =Annahmen!C17 -> 750 | I22: =Annahmen!C18 -> 750 | J22: =SUMIFS(Monatlich!$E$4:$E$63,Monatlich!$A$4:$A$63,"Ja",Monatlich!$H$4:$H$63,"Theo",Monatlich!$D$4:$D$63,"Ausgabe",Monatlich!$J$4:$J$63,"<="&$A22,Monatlich!$K$4:$K$63,">="&$A22)+SUMIFS(Einmalig!$E$4:$E$43,Einmalig!$A$4:$A$43,"Ja",Einmalig!$G$4:$G$43,"Theo",Einmalig!$D$4:$D$43,"Ausgabe",Einmalig!$I$4:$I$43,$A22) -> 0 | K22: =SUMIFS(Monatlich!$E$4:$E$63,Monatlich!$A$4:$A$63,"Ja",Monatlich!$H$4:$H$63,"Jule",Monatlich!$D$4:$D$63,"Ausgabe",Monatlich!$J$4:$J$63,"<="&$A22,Monatlich!$K$4:$K$63,">="&$A22)+SUMIFS(Einmalig!$E$4:$E$43,Einmalig!$A$4:$A$43,"Ja",Einmalig!$G$4:$G$43,"Jule",Einmalig!$D$4:$D$43,"Ausgabe",Einmalig!$I$4:$I$43,$A22) -> 0 | L22: =SUMIFS(Monatlich!$E$4:$E$63,Monatlich!$A$4:$A$63,"Ja",Monatlich!$H$4:$H$63,"Gemeinsam",Monatlich!$D$4:$D$63,"Ausgabe",Monatlich!$J$4:$J$63,"<="&$A22,Monatlich!$K$4:$K$63,">="&$A22)+SUMIFS(Einmalig!$E$4:$E$43,Einmalig!$A$4:$A$43,"Ja",Einmalig!$G$4:$G$43,"Gemeinsam",Einmalig!$D$4:$D$43,"Ausgabe",Einmalig!$I$4:$I$43,$A22) -> 2500 | M22: =SUM(H22:L22) -> 4000 | N22: =G22-M22 -> 3522.3205 | O22: =MAX(0,(Q21+B22+D22-H22-J22)-Annahmen!C19) -> 4166.8605 | P22: =MAX(0,(R21+C22+E22-I22-K22)-Annahmen!C20) -> 1855.46 | Q22: =(Q21+B22+D22-H22-J22)-O22 -> 0 | R22: =(R21+C22+E22-I22-K22)-P22 -> 0 | S22: =S21+O22+P22+F22-L22 -> 89667.846 | T22: =Q22+R22+S22 -> 89667.846
A23: =DATE(YEAR(A22),MONTH(A22)+1,1) -> 46631 | B23: =Annahmen!C55 -> 4916.8605 | C23: =Annahmen!D55 -> 2605.46 | D23: =SUMIFS(Monatlich!$E$4:$E$63,Monatlich!$A$4:$A$63,"Ja",Monatlich!$H$4:$H$63,"Theo",Monatlich!$D$4:$D$63,"Einnahme",Monatlich!$J$4:$J$63,"<="&$A23,Monatlich!$K$4:$K$63,">="&$A23)+SUMIFS(Einmalig!$E$4:$E$43,Einmalig!$A$4:$A$43,"Ja",Einmalig!$G$4:$G$43,"Theo",Einmalig!$D$4:$D$43,"Einnahme",Einmalig!$I$4:$I$43,$A23) -> 0 | E23: =SUMIFS(Monatlich!$E$4:$E$63,Monatlich!$A$4:$A$63,"Ja",Monatlich!$H$4:$H$63,"Jule",Monatlich!$D$4:$D$63,"Einnahme",Monatlich!$J$4:$J$63,"<="&$A23,Monatlich!$K$4:$K$63,">="&$A23)+SUMIFS(Einmalig!$E$4:$E$43,Einmalig!$A$4:$A$43,"Ja",Einmalig!$G$4:$G$43,"Jule",Einmalig!$D$4:$D$43,"Einnahme",Einmalig!$I$4:$I$43,$A23) -> 0 | F23: =SUMIFS(Monatlich!$E$4:$E$63,Monatlich!$A$4:$A$63,"Ja",Monatlich!$H$4:$H$63,"Gemeinsam",Monatlich!$D$4:$D$63,"Einnahme",Monatlich!$J$4:$J$63,"<="&$A23,Monatlich!$K$4:$K$63,">="&$A23)+SUMIFS(Einmalig!$E$4:$E$43,Einmalig!$A$4:$A$43,"Ja",Einmalig!$G$4:$G$43,"Gemeinsam",Einmalig!$D$4:$D$43,"Einnahme",Einmalig!$I$4:$I$43,$A23) -> 0 | G23: =SUM(B23:F23) -> 7522.3205 | H23: =Annahmen!C17 -> 750 | I23: =Annahmen!C18 -> 750 | J23: =SUMIFS(Monatlich!$E$4:$E$63,Monatlich!$A$4:$A$63,"Ja",Monatlich!$H$4:$H$63,"Theo",Monatlich!$D$4:$D$63,"Ausgabe",Monatlich!$J$4:$J$63,"<="&$A23,Monatlich!$K$4:$K$63,">="&$A23)+SUMIFS(Einmalig!$E$4:$E$43,Einmalig!$A$4:$A$43,"Ja",Einmalig!$G$4:$G$43,"Theo",Einmalig!$D$4:$D$43,"Ausgabe",Einmalig!$I$4:$I$43,$A23) -> 0 | K23: =SUMIFS(Monatlich!$E$4:$E$63,Monatlich!$A$4:$A$63,"Ja",Monatlich!$H$4:$H$63,"Jule",Monatlich!$D$4:$D$63,"Ausgabe",Monatlich!$J$4:$J$63,"<="&$A23,Monatlich!$K$4:$K$63,">="&$A23)+SUMIFS(Einmalig!$E$4:$E$43,Einmalig!$A$4:$A$43,"Ja",Einmalig!$G$4:$G$43,"Jule",Einmalig!$D$4:$D$43,"Ausgabe",Einmalig!$I$4:$I$43,$A23) -> 0 | L23: =SUMIFS(Monatlich!$E$4:$E$63,Monatlich!$A$4:$A$63,"Ja",Monatlich!$H$4:$H$63,"Gemeinsam",Monatlich!$D$4:$D$63,"Ausgabe",Monatlich!$J$4:$J$63,"<="&$A23,Monatlich!$K$4:$K$63,">="&$A23)+SUMIFS(Einmalig!$E$4:$E$43,Einmalig!$A$4:$A$43,"Ja",Einmalig!$G$4:$G$43,"Gemeinsam",Einmalig!$D$4:$D$43,"Ausgabe",Einmalig!$I$4:$I$43,$A23) -> 2500 | M23: =SUM(H23:L23) -> 4000 | N23: =G23-M23 -> 3522.3205 | O23: =MAX(0,(Q22+B23+D23-H23-J23)-Annahmen!C19) -> 4166.8605 | P23: =MAX(0,(R22+C23+E23-I23-K23)-Annahmen!C20) -> 1855.46 | Q23: =(Q22+B23+D23-H23-J23)-O23 -> 0 | R23: =(R22+C23+E23-I23-K23)-P23 -> 0 | S23: =S22+O23+P23+F23-L23 -> 93190.167 | T23: =Q23+R23+S23 -> 93190.167
A24: =DATE(YEAR(A23),MONTH(A23)+1,1) -> 46661 | B24: =Annahmen!C55 -> 4916.8605 | C24: =Annahmen!D55 -> 2605.46 | D24: =SUMIFS(Monatlich!$E$4:$E$63,Monatlich!$A$4:$A$63,"Ja",Monatlich!$H$4:$H$63,"Theo",Monatlich!$D$4:$D$63,"Einnahme",Monatlich!$J$4:$J$63,"<="&$A24,Monatlich!$K$4:$K$63,">="&$A24)+SUMIFS(Einmalig!$E$4:$E$43,Einmalig!$A$4:$A$43,"Ja",Einmalig!$G$4:$G$43,"Theo",Einmalig!$D$4:$D$43,"Einnahme",Einmalig!$I$4:$I$43,$A24) -> 0 | E24: =SUMIFS(Monatlich!$E$4:$E$63,Monatlich!$A$4:$A$63,"Ja",Monatlich!$H$4:$H$63,"Jule",Monatlich!$D$4:$D$63,"Einnahme",Monatlich!$J$4:$J$63,"<="&$A24,Monatlich!$K$4:$K$63,">="&$A24)+SUMIFS(Einmalig!$E$4:$E$43,Einmalig!$A$4:$A$43,"Ja",Einmalig!$G$4:$G$43,"Jule",Einmalig!$D$4:$D$43,"Einnahme",Einmalig!$I$4:$I$43,$A24) -> 0 | F24: =SUMIFS(Monatlich!$E$4:$E$63,Monatlich!$A$4:$A$63,"Ja",Monatlich!$H$4:$H$63,"Gemeinsam",Monatlich!$D$4:$D$63,"Einnahme",Monatlich!$J$4:$J$63,"<="&$A24,Monatlich!$K$4:$K$63,">="&$A24)+SUMIFS(Einmalig!$E$4:$E$43,Einmalig!$A$4:$A$43,"Ja",Einmalig!$G$4:$G$43,"Gemeinsam",Einmalig!$D$4:$D$43,"Einnahme",Einmalig!$I$4:$I$43,$A24) -> 0 | G24: =SUM(B24:F24) -> 7522.3205 | H24: =Annahmen!C17 -> 750 | I24: =Annahmen!C18 -> 750 | J24: =SUMIFS(Monatlich!$E$4:$E$63,Monatlich!$A$4:$A$63,"Ja",Monatlich!$H$4:$H$63,"Theo",Monatlich!$D$4:$D$63,"Ausgabe",Monatlich!$J$4:$J$63,"<="&$A24,Monatlich!$K$4:$K$63,">="&$A24)+SUMIFS(Einmalig!$E$4:$E$43,Einmalig!$A$4:$A$43,"Ja",Einmalig!$G$4:$G$43,"Theo",Einmalig!$D$4:$D$43,"Ausgabe",Einmalig!$I$4:$I$43,$A24) -> 0 | K24: =SUMIFS(Monatlich!$E$4:$E$63,Monatlich!$A$4:$A$63,"Ja",Monatlich!$H$4:$H$63,"Jule",Monatlich!$D$4:$D$63,"Ausgabe",Monatlich!$J$4:$J$63,"<="&$A24,Monatlich!$K$4:$K$63,">="&$A24)+SUMIFS(Einmalig!$E$4:$E$43,Einmalig!$A$4:$A$43,"Ja",Einmalig!$G$4:$G$43,"Jule",Einmalig!$D$4:$D$43,"Ausgabe",Einmalig!$I$4:$I$43,$A24) -> 0 | L24: =SUMIFS(Monatlich!$E$4:$E$63,Monatlich!$A$4:$A$63,"Ja",Monatlich!$H$4:$H$63,"Gemeinsam",Monatlich!$D$4:$D$63,"Ausgabe",Monatlich!$J$4:$J$63,"<="&$A24,Monatlich!$K$4:$K$63,">="&$A24)+SUMIFS(Einmalig!$E$4:$E$43,Einmalig!$A$4:$A$43,"Ja",Einmalig!$G$4:$G$43,"Gemeinsam",Einmalig!$D$4:$D$43,"Ausgabe",Einmalig!$I$4:$I$43,$A24) -> 2500 | M24: =SUM(H24:L24) -> 4000 | N24: =G24-M24 -> 3522.3205 | O24: =MAX(0,(Q23+B24+D24-H24-J24)-Annahmen!C19) -> 4166.8605 | P24: =MAX(0,(R23+C24+E24-I24-K24)-Annahmen!C20) -> 1855.46 | Q24: =(Q23+B24+D24-H24-J24)-O24 -> 0 | R24: =(R23+C24+E24-I24-K24)-P24 -> 0 | S24: =S23+O24+P24+F24-L24 -> 96712.487 | T24: =Q24+R24+S24 -> 96712.487
A25: =DATE(YEAR(A24),MONTH(A24)+1,1) -> 46692 | B25: =Annahmen!C55 -> 4916.8605 | C25: =Annahmen!D55 -> 2605.46 | D25: =SUMIFS(Monatlich!$E$4:$E$63,Monatlich!$A$4:$A$63,"Ja",Monatlich!$H$4:$H$63,"Theo",Monatlich!$D$4:$D$63,"Einnahme",Monatlich!$J$4:$J$63,"<="&$A25,Monatlich!$K$4:$K$63,">="&$A25)+SUMIFS(Einmalig!$E$4:$E$43,Einmalig!$A$4:$A$43,"Ja",Einmalig!$G$4:$G$43,"Theo",Einmalig!$D$4:$D$43,"Einnahme",Einmalig!$I$4:$I$43,$A25) -> 900 | E25: =SUMIFS(Monatlich!$E$4:$E$63,Monatlich!$A$4:$A$63,"Ja",Monatlich!$H$4:$H$63,"Jule",Monatlich!$D$4:$D$63,"Einnahme",Monatlich!$J$4:$J$63,"<="&$A25,Monatlich!$K$4:$K$63,">="&$A25)+SUMIFS(Einmalig!$E$4:$E$43,Einmalig!$A$4:$A$43,"Ja",Einmalig!$G$4:$G$43,"Jule",Einmalig!$D$4:$D$43,"Einnahme",Einmalig!$I$4:$I$43,$A25) -> 0 | F25: =SUMIFS(Monatlich!$E$4:$E$63,Monatlich!$A$4:$A$63,"Ja",Monatlich!$H$4:$H$63,"Gemeinsam",Monatlich!$D$4:$D$63,"Einnahme",Monatlich!$J$4:$J$63,"<="&$A25,Monatlich!$K$4:$K$63,">="&$A25)+SUMIFS(Einmalig!$E$4:$E$43,Einmalig!$A$4:$A$43,"Ja",Einmalig!$G$4:$G$43,"Gemeinsam",Einmalig!$D$4:$D$43,"Einnahme",Einmalig!$I$4:$I$43,$A25) -> 0 | G25: =SUM(B25:F25) -> 8422.3205 | H25: =Annahmen!C17 -> 750 | I25: =Annahmen!C18 -> 750 | J25: =SUMIFS(Monatlich!$E$4:$E$63,Monatlich!$A$4:$A$63,"Ja",Monatlich!$H$4:$H$63,"Theo",Monatlich!$D$4:$D$63,"Ausgabe",Monatlich!$J$4:$J$63,"<="&$A25,Monatlich!$K$4:$K$63,">="&$A25)+SUMIFS(Einmalig!$E$4:$E$43,Einmalig!$A$4:$A$43,"Ja",Einmalig!$G$4:$G$43,"Theo",Einmalig!$D$4:$D$43,"Ausgabe",Einmalig!$I$4:$I$43,$A25) -> 0 | K25: =SUMIFS(Monatlich!$E$4:$E$63,Monatlich!$A$4:$A$63,"Ja",Monatlich!$H$4:$H$63,"Jule",Monatlich!$D$4:$D$63,"Ausgabe",Monatlich!$J$4:$J$63,"<="&$A25,Monatlich!$K$4:$K$63,">="&$A25)+SUMIFS(Einmalig!$E$4:$E$43,Einmalig!$A$4:$A$43,"Ja",Einmalig!$G$4:$G$43,"Jule",Einmalig!$D$4:$D$43,"Ausgabe",Einmalig!$I$4:$I$43,$A25) -> 0 | L25: =SUMIFS(Monatlich!$E$4:$E$63,Monatlich!$A$4:$A$63,"Ja",Monatlich!$H$4:$H$63,"Gemeinsam",Monatlich!$D$4:$D$63,"Ausgabe",Monatlich!$J$4:$J$63,"<="&$A25,Monatlich!$K$4:$K$63,">="&$A25)+SUMIFS(Einmalig!$E$4:$E$43,Einmalig!$A$4:$A$43,"Ja",Einmalig!$G$4:$G$43,"Gemeinsam",Einmalig!$D$4:$D$43,"Ausgabe",Einmalig!$I$4:$I$43,$A25) -> 18500 | M25: =SUM(H25:L25) -> 20000 | N25: =G25-M25 -> -11577.679 | O25: =MAX(0,(Q24+B25+D25-H25-J25)-Annahmen!C19) -> 5066.8605 | P25: =MAX(0,(R24+C25+E25-I25-K25)-Annahmen!C20) -> 1855.46 | Q25: =(Q24+B25+D25-H25-J25)-O25 -> 0 | R25: =(R24+C25+E25-I25-K25)-P25 -> 0 | S25: =S24+O25+P25+F25-L25 -> 85134.808 | T25: =Q25+R25+S25 -> 85134.808
A26: =DATE(YEAR(A25),MONTH(A25)+1,1) -> 46722 | B26: =Annahmen!C55 -> 4916.8605 | C26: =Annahmen!D55 -> 2605.46 | D26: =SUMIFS(Monatlich!$E$4:$E$63,Monatlich!$A$4:$A$63,"Ja",Monatlich!$H$4:$H$63,"Theo",Monatlich!$D$4:$D$63,"Einnahme",Monatlich!$J$4:$J$63,"<="&$A26,Monatlich!$K$4:$K$63,">="&$A26)+SUMIFS(Einmalig!$E$4:$E$43,Einmalig!$A$4:$A$43,"Ja",Einmalig!$G$4:$G$43,"Theo",Einmalig!$D$4:$D$43,"Einnahme",Einmalig!$I$4:$I$43,$A26) -> 0 | E26: =SUMIFS(Monatlich!$E$4:$E$63,Monatlich!$A$4:$A$63,"Ja",Monatlich!$H$4:$H$63,"Jule",Monatlich!$D$4:$D$63,"Einnahme",Monatlich!$J$4:$J$63,"<="&$A26,Monatlich!$K$4:$K$63,">="&$A26)+SUMIFS(Einmalig!$E$4:$E$43,Einmalig!$A$4:$A$43,"Ja",Einmalig!$G$4:$G$43,"Jule",Einmalig!$D$4:$D$43,"Einnahme",Einmalig!$I$4:$I$43,$A26) -> 0 | F26: =SUMIFS(Monatlich!$E$4:$E$63,Monatlich!$A$4:$A$63,"Ja",Monatlich!$H$4:$H$63,"Gemeinsam",Monatlich!$D$4:$D$63,"Einnahme",Monatlich!$J$4:$J$63,"<="&$A26,Monatlich!$K$4:$K$63,">="&$A26)+SUMIFS(Einmalig!$E$4:$E$43,Einmalig!$A$4:$A$43,"Ja",Einmalig!$G$4:$G$43,"Gemeinsam",Einmalig!$D$4:$D$43,"Einnahme",Einmalig!$I$4:$I$43,$A26) -> 0 | G26: =SUM(B26:F26) -> 7522.3205 | H26: =Annahmen!C17 -> 750 | I26: =Annahmen!C18 -> 750 | J26: =SUMIFS(Monatlich!$E$4:$E$63,Monatlich!$A$4:$A$63,"Ja",Monatlich!$H$4:$H$63,"Theo",Monatlich!$D$4:$D$63,"Ausgabe",Monatlich!$J$4:$J$63,"<="&$A26,Monatlich!$K$4:$K$63,">="&$A26)+SUMIFS(Einmalig!$E$4:$E$43,Einmalig!$A$4:$A$43,"Ja",Einmalig!$G$4:$G$43,"Theo",Einmalig!$D$4:$D$43,"Ausgabe",Einmalig!$I$4:$I$43,$A26) -> 0 | K26: =SUMIFS(Monatlich!$E$4:$E$63,Monatlich!$A$4:$A$63,"Ja",Monatlich!$H$4:$H$63,"Jule",Monatlich!$D$4:$D$63,"Ausgabe",Monatlich!$J$4:$J$63,"<="&$A26,Monatlich!$K$4:$K$63,">="&$A26)+SUMIFS(Einmalig!$E$4:$E$43,Einmalig!$A$4:$A$43,"Ja",Einmalig!$G$4:$G$43,"Jule",Einmalig!$D$4:$D$43,"Ausgabe",Einmalig!$I$4:$I$43,$A26) -> 0 | L26: =SUMIFS(Monatlich!$E$4:$E$63,Monatlich!$A$4:$A$63,"Ja",Monatlich!$H$4:$H$63,"Gemeinsam",Monatlich!$D$4:$D$63,"Ausgabe",Monatlich!$J$4:$J$63,"<="&$A26,Monatlich!$K$4:$K$63,">="&$A26)+SUMIFS(Einmalig!$E$4:$E$43,Einmalig!$A$4:$A$43,"Ja",Einmalig!$G$4:$G$43,"Gemeinsam",Einmalig!$D$4:$D$43,"Ausgabe",Einmalig!$I$4:$I$43,$A26) -> 2500 | M26: =SUM(H26:L26) -> 4000 | N26: =G26-M26 -> 3522.3205 | O26: =MAX(0,(Q25+B26+D26-H26-J26)-Annahmen!C19) -> 4166.8605 | P26: =MAX(0,(R25+C26+E26-I26-K26)-Annahmen!C20) -> 1855.46 | Q26: =(Q25+B26+D26-H26-J26)-O26 -> 0 | R26: =(R25+C26+E26-I26-K26)-P26 -> 0 | S26: =S25+O26+P26+F26-L26 -> 88657.128 | T26: =Q26+R26+S26 -> 88657.128
A27: =DATE(YEAR(A26),MONTH(A26)+1,1) -> 46753 | B27: =Annahmen!C55 -> 4916.8605 | C27: =Annahmen!D55 -> 2605.46 | D27: =SUMIFS(Monatlich!$E$4:$E$63,Monatlich!$A$4:$A$63,"Ja",Monatlich!$H$4:$H$63,"Theo",Monatlich!$D$4:$D$63,"Einnahme",Monatlich!$J$4:$J$63,"<="&$A27,Monatlich!$K$4:$K$63,">="&$A27)+SUMIFS(Einmalig!$E$4:$E$43,Einmalig!$A$4:$A$43,"Ja",Einmalig!$G$4:$G$43,"Theo",Einmalig!$D$4:$D$43,"Einnahme",Einmalig!$I$4:$I$43,$A27) -> 0 | E27: =SUMIFS(Monatlich!$E$4:$E$63,Monatlich!$A$4:$A$63,"Ja",Monatlich!$H$4:$H$63,"Jule",Monatlich!$D$4:$D$63,"Einnahme",Monatlich!$J$4:$J$63,"<="&$A27,Monatlich!$K$4:$K$63,">="&$A27)+SUMIFS(Einmalig!$E$4:$E$43,Einmalig!$A$4:$A$43,"Ja",Einmalig!$G$4:$G$43,"Jule",Einmalig!$D$4:$D$43,"Einnahme",Einmalig!$I$4:$I$43,$A27) -> 0 | F27: =SUMIFS(Monatlich!$E$4:$E$63,Monatlich!$A$4:$A$63,"Ja",Monatlich!$H$4:$H$63,"Gemeinsam",Monatlich!$D$4:$D$63,"Einnahme",Monatlich!$J$4:$J$63,"<="&$A27,Monatlich!$K$4:$K$63,">="&$A27)+SUMIFS(Einmalig!$E$4:$E$43,Einmalig!$A$4:$A$43,"Ja",Einmalig!$G$4:$G$43,"Gemeinsam",Einmalig!$D$4:$D$43,"Einnahme",Einmalig!$I$4:$I$43,$A27) -> 0 | G27: =SUM(B27:F27) -> 7522.3205 | H27: =Annahmen!C17 -> 750 | I27: =Annahmen!C18 -> 750 | J27: =SUMIFS(Monatlich!$E$4:$E$63,Monatlich!$A$4:$A$63,"Ja",Monatlich!$H$4:$H$63,"Theo",Monatlich!$D$4:$D$63,"Ausgabe",Monatlich!$J$4:$J$63,"<="&$A27,Monatlich!$K$4:$K$63,">="&$A27)+SUMIFS(Einmalig!$E$4:$E$43,Einmalig!$A$4:$A$43,"Ja",Einmalig!$G$4:$G$43,"Theo",Einmalig!$D$4:$D$43,"Ausgabe",Einmalig!$I$4:$I$43,$A27) -> 0 | K27: =SUMIFS(Monatlich!$E$4:$E$63,Monatlich!$A$4:$A$63,"Ja",Monatlich!$H$4:$H$63,"Jule",Monatlich!$D$4:$D$63,"Ausgabe",Monatlich!$J$4:$J$63,"<="&$A27,Monatlich!$K$4:$K$63,">="&$A27)+SUMIFS(Einmalig!$E$4:$E$43,Einmalig!$A$4:$A$43,"Ja",Einmalig!$G$4:$G$43,"Jule",Einmalig!$D$4:$D$43,"Ausgabe",Einmalig!$I$4:$I$43,$A27) -> 0 | L27: =SUMIFS(Monatlich!$E$4:$E$63,Monatlich!$A$4:$A$63,"Ja",Monatlich!$H$4:$H$63,"Gemeinsam",Monatlich!$D$4:$D$63,"Ausgabe",Monatlich!$J$4:$J$63,"<="&$A27,Monatlich!$K$4:$K$63,">="&$A27)+SUMIFS(Einmalig!$E$4:$E$43,Einmalig!$A$4:$A$43,"Ja",Einmalig!$G$4:$G$43,"Gemeinsam",Einmalig!$D$4:$D$43,"Ausgabe",Einmalig!$I$4:$I$43,$A27) -> 2500 | M27: =SUM(H27:L27) -> 4000 | N27: =G27-M27 -> 3522.3205 | O27: =MAX(0,(Q26+B27+D27-H27-J27)-Annahmen!C19) -> 4166.8605 | P27: =MAX(0,(R26+C27+E27-I27-K27)-Annahmen!C20) -> 1855.46 | Q27: =(Q26+B27+D27-H27-J27)-O27 -> 0 | R27: =(R26+C27+E27-I27-K27)-P27 -> 0 | S27: =S26+O27+P27+F27-L27 -> 92179.449 | T27: =Q27+R27+S27 -> 92179.449
A28: =DATE(YEAR(A27),MONTH(A27)+1,1) -> 46784 | B28: =Annahmen!C55 -> 4916.8605 | C28: =Annahmen!D55 -> 2605.46 | D28: =SUMIFS(Monatlich!$E$4:$E$63,Monatlich!$A$4:$A$63,"Ja",Monatlich!$H$4:$H$63,"Theo",Monatlich!$D$4:$D$63,"Einnahme",Monatlich!$J$4:$J$63,"<="&$A28,Monatlich!$K$4:$K$63,">="&$A28)+SUMIFS(Einmalig!$E$4:$E$43,Einmalig!$A$4:$A$43,"Ja",Einmalig!$G$4:$G$43,"Theo",Einmalig!$D$4:$D$43,"Einnahme",Einmalig!$I$4:$I$43,$A28) -> 0 | E28: =SUMIFS(Monatlich!$E$4:$E$63,Monatlich!$A$4:$A$63,"Ja",Monatlich!$H$4:$H$63,"Jule",Monatlich!$D$4:$D$63,"Einnahme",Monatlich!$J$4:$J$63,"<="&$A28,Monatlich!$K$4:$K$63,">="&$A28)+SUMIFS(Einmalig!$E$4:$E$43,Einmalig!$A$4:$A$43,"Ja",Einmalig!$G$4:$G$43,"Jule",Einmalig!$D$4:$D$43,"Einnahme",Einmalig!$I$4:$I$43,$A28) -> 0 | F28: =SUMIFS(Monatlich!$E$4:$E$63,Monatlich!$A$4:$A$63,"Ja",Monatlich!$H$4:$H$63,"Gemeinsam",Monatlich!$D$4:$D$63,"Einnahme",Monatlich!$J$4:$J$63,"<="&$A28,Monatlich!$K$4:$K$63,">="&$A28)+SUMIFS(Einmalig!$E$4:$E$43,Einmalig!$A$4:$A$43,"Ja",Einmalig!$G$4:$G$43,"Gemeinsam",Einmalig!$D$4:$D$43,"Einnahme",Einmalig!$I$4:$I$43,$A28) -> 0 | G28: =SUM(B28:F28) -> 7522.3205 | H28: =Annahmen!C17 -> 750 | I28: =Annahmen!C18 -> 750 | J28: =SUMIFS(Monatlich!$E$4:$E$63,Monatlich!$A$4:$A$63,"Ja",Monatlich!$H$4:$H$63,"Theo",Monatlich!$D$4:$D$63,"Ausgabe",Monatlich!$J$4:$J$63,"<="&$A28,Monatlich!$K$4:$K$63,">="&$A28)+SUMIFS(Einmalig!$E$4:$E$43,Einmalig!$A$4:$A$43,"Ja",Einmalig!$G$4:$G$43,"Theo",Einmalig!$D$4:$D$43,"Ausgabe",Einmalig!$I$4:$I$43,$A28) -> 0 | K28: =SUMIFS(Monatlich!$E$4:$E$63,Monatlich!$A$4:$A$63,"Ja",Monatlich!$H$4:$H$63,"Jule",Monatlich!$D$4:$D$63,"Ausgabe",Monatlich!$J$4:$J$63,"<="&$A28,Monatlich!$K$4:$K$63,">="&$A28)+SUMIFS(Einmalig!$E$4:$E$43,Einmalig!$A$4:$A$43,"Ja",Einmalig!$G$4:$G$43,"Jule",Einmalig!$D$4:$D$43,"Ausgabe",Einmalig!$I$4:$I$43,$A28) -> 0 | L28: =SUMIFS(Monatlich!$E$4:$E$63,Monatlich!$A$4:$A$63,"Ja",Monatlich!$H$4:$H$63,"Gemeinsam",Monatlich!$D$4:$D$63,"Ausgabe",Monatlich!$J$4:$J$63,"<="&$A28,Monatlich!$K$4:$K$63,">="&$A28)+SUMIFS(Einmalig!$E$4:$E$43,Einmalig!$A$4:$A$43,"Ja",Einmalig!$G$4:$G$43,"Gemeinsam",Einmalig!$D$4:$D$43,"Ausgabe",Einmalig!$I$4:$I$43,$A28) -> 2500 | M28: =SUM(H28:L28) -> 4000 | N28: =G28-M28 -> 3522.3205 | O28: =MAX(0,(Q27+B28+D28-H28-J28)-Annahmen!C19) -> 4166.8605 | P28: =MAX(0,(R27+C28+E28-I28-K28)-Annahmen!C20) -> 1855.46 | Q28: =(Q27+B28+D28-H28-J28)-O28 -> 0 | R28: =(R27+C28+E28-I28-K28)-P28 -> 0 | S28: =S27+O28+P28+F28-L28 -> 95701.769 | T28: =Q28+R28+S28 -> 95701.769
A29: =DATE(YEAR(A28),MONTH(A28)+1,1) -> 46813 | B29: =Annahmen!C55 -> 4916.8605 | C29: =Annahmen!D55 -> 2605.46 | D29: =SUMIFS(Monatlich!$E$4:$E$63,Monatlich!$A$4:$A$63,"Ja",Monatlich!$H$4:$H$63,"Theo",Monatlich!$D$4:$D$63,"Einnahme",Monatlich!$J$4:$J$63,"<="&$A29,Monatlich!$K$4:$K$63,">="&$A29)+SUMIFS(Einmalig!$E$4:$E$43,Einmalig!$A$4:$A$43,"Ja",Einmalig!$G$4:$G$43,"Theo",Einmalig!$D$4:$D$43,"Einnahme",Einmalig!$I$4:$I$43,$A29) -> 0 | E29: =SUMIFS(Monatlich!$E$4:$E$63,Monatlich!$A$4:$A$63,"Ja",Monatlich!$H$4:$H$63,"Jule",Monatlich!$D$4:$D$63,"Einnahme",Monatlich!$J$4:$J$63,"<="&$A29,Monatlich!$K$4:$K$63,">="&$A29)+SUMIFS(Einmalig!$E$4:$E$43,Einmalig!$A$4:$A$43,"Ja",Einmalig!$G$4:$G$43,"Jule",Einmalig!$D$4:$D$43,"Einnahme",Einmalig!$I$4:$I$43,$A29) -> 0 | F29: =SUMIFS(Monatlich!$E$4:$E$63,Monatlich!$A$4:$A$63,"Ja",Monatlich!$H$4:$H$63,"Gemeinsam",Monatlich!$D$4:$D$63,"Einnahme",Monatlich!$J$4:$J$63,"<="&$A29,Monatlich!$K$4:$K$63,">="&$A29)+SUMIFS(Einmalig!$E$4:$E$43,Einmalig!$A$4:$A$43,"Ja",Einmalig!$G$4:$G$43,"Gemeinsam",Einmalig!$D$4:$D$43,"Einnahme",Einmalig!$I$4:$I$43,$A29) -> 0 | G29: =SUM(B29:F29) -> 7522.3205 | H29: =Annahmen!C17 -> 750 | I29: =Annahmen!C18 -> 750 | J29: =SUMIFS(Monatlich!$E$4:$E$63,Monatlich!$A$4:$A$63,"Ja",Monatlich!$H$4:$H$63,"Theo",Monatlich!$D$4:$D$63,"Ausgabe",Monatlich!$J$4:$J$63,"<="&$A29,Monatlich!$K$4:$K$63,">="&$A29)+SUMIFS(Einmalig!$E$4:$E$43,Einmalig!$A$4:$A$43,"Ja",Einmalig!$G$4:$G$43,"Theo",Einmalig!$D$4:$D$43,"Ausgabe",Einmalig!$I$4:$I$43,$A29) -> 0 | K29: =SUMIFS(Monatlich!$E$4:$E$63,Monatlich!$A$4:$A$63,"Ja",Monatlich!$H$4:$H$63,"Jule",Monatlich!$D$4:$D$63,"Ausgabe",Monatlich!$J$4:$J$63,"<="&$A29,Monatlich!$K$4:$K$63,">="&$A29)+SUMIFS(Einmalig!$E$4:$E$43,Einmalig!$A$4:$A$43,"Ja",Einmalig!$G$4:$G$43,"Jule",Einmalig!$D$4:$D$43,"Ausgabe",Einmalig!$I$4:$I$43,$A29) -> 0 | L29: =SUMIFS(Monatlich!$E$4:$E$63,Monatlich!$A$4:$A$63,"Ja",Monatlich!$H$4:$H$63,"Gemeinsam",Monatlich!$D$4:$D$63,"Ausgabe",Monatlich!$J$4:$J$63,"<="&$A29,Monatlich!$K$4:$K$63,">="&$A29)+SUMIFS(Einmalig!$E$4:$E$43,Einmalig!$A$4:$A$43,"Ja",Einmalig!$G$4:$G$43,"Gemeinsam",Einmalig!$D$4:$D$43,"Ausgabe",Einmalig!$I$4:$I$43,$A29) -> 2500 | M29: =SUM(H29:L29) -> 4000 | N29: =G29-M29 -> 3522.3205 | O29: =MAX(0,(Q28+B29+D29-H29-J29)-Annahmen!C19) -> 4166.8605 | P29: =MAX(0,(R28+C29+E29-I29-K29)-Annahmen!C20) -> 1855.46 | Q29: =(Q28+B29+D29-H29-J29)-O29 -> 0 | R29: =(R28+C29+E29-I29-K29)-P29 -> 0 | S29: =S28+O29+P29+F29-L29 -> 99224.09 | T29: =Q29+R29+S29 -> 99224.09
A30: =DATE(YEAR(A29),MONTH(A29)+1,1) -> 46844 | B30: =Annahmen!C55 -> 4916.8605 | C30: =Annahmen!D55 -> 2605.46 | D30: =SUMIFS(Monatlich!$E$4:$E$63,Monatlich!$A$4:$A$63,"Ja",Monatlich!$H$4:$H$63,"Theo",Monatlich!$D$4:$D$63,"Einnahme",Monatlich!$J$4:$J$63,"<="&$A30,Monatlich!$K$4:$K$63,">="&$A30)+SUMIFS(Einmalig!$E$4:$E$43,Einmalig!$A$4:$A$43,"Ja",Einmalig!$G$4:$G$43,"Theo",Einmalig!$D$4:$D$43,"Einnahme",Einmalig!$I$4:$I$43,$A30) -> 0 | E30: =SUMIFS(Monatlich!$E$4:$E$63,Monatlich!$A$4:$A$63,"Ja",Monatlich!$H$4:$H$63,"Jule",Monatlich!$D$4:$D$63,"Einnahme",Monatlich!$J$4:$J$63,"<="&$A30,Monatlich!$K$4:$K$63,">="&$A30)+SUMIFS(Einmalig!$E$4:$E$43,Einmalig!$A$4:$A$43,"Ja",Einmalig!$G$4:$G$43,"Jule",Einmalig!$D$4:$D$43,"Einnahme",Einmalig!$I$4:$I$43,$A30) -> 0 | F30: =SUMIFS(Monatlich!$E$4:$E$63,Monatlich!$A$4:$A$63,"Ja",Monatlich!$H$4:$H$63,"Gemeinsam",Monatlich!$D$4:$D$63,"Einnahme",Monatlich!$J$4:$J$63,"<="&$A30,Monatlich!$K$4:$K$63,">="&$A30)+SUMIFS(Einmalig!$E$4:$E$43,Einmalig!$A$4:$A$43,"Ja",Einmalig!$G$4:$G$43,"Gemeinsam",Einmalig!$D$4:$D$43,"Einnahme",Einmalig!$I$4:$I$43,$A30) -> 0 | G30: =SUM(B30:F30) -> 7522.3205 | H30: =Annahmen!C17 -> 750 | I30: =Annahmen!C18 -> 750 | J30: =SUMIFS(Monatlich!$E$4:$E$63,Monatlich!$A$4:$A$63,"Ja",Monatlich!$H$4:$H$63,"Theo",Monatlich!$D$4:$D$63,"Ausgabe",Monatlich!$J$4:$J$63,"<="&$A30,Monatlich!$K$4:$K$63,">="&$A30)+SUMIFS(Einmalig!$E$4:$E$43,Einmalig!$A$4:$A$43,"Ja",Einmalig!$G$4:$G$43,"Theo",Einmalig!$D$4:$D$43,"Ausgabe",Einmalig!$I$4:$I$43,$A30) -> 0 | K30: =SUMIFS(Monatlich!$E$4:$E$63,Monatlich!$A$4:$A$63,"Ja",Monatlich!$H$4:$H$63,"Jule",Monatlich!$D$4:$D$63,"Ausgabe",Monatlich!$J$4:$J$63,"<="&$A30,Monatlich!$K$4:$K$63,">="&$A30)+SUMIFS(Einmalig!$E$4:$E$43,Einmalig!$A$4:$A$43,"Ja",Einmalig!$G$4:$G$43,"Jule",Einmalig!$D$4:$D$43,"Ausgabe",Einmalig!$I$4:$I$43,$A30) -> 0 | L30: =SUMIFS(Monatlich!$E$4:$E$63,Monatlich!$A$4:$A$63,"Ja",Monatlich!$H$4:$H$63,"Gemeinsam",Monatlich!$D$4:$D$63,"Ausgabe",Monatlich!$J$4:$J$63,"<="&$A30,Monatlich!$K$4:$K$63,">="&$A30)+SUMIFS(Einmalig!$E$4:$E$43,Einmalig!$A$4:$A$43,"Ja",Einmalig!$G$4:$G$43,"Gemeinsam",Einmalig!$D$4:$D$43,"Ausgabe",Einmalig!$I$4:$I$43,$A30) -> 2500 | M30: =SUM(H30:L30) -> 4000 | N30: =G30-M30 -> 3522.3205 | O30: =MAX(0,(Q29+B30+D30-H30-J30)-Annahmen!C19) -> 4166.8605 | P30: =MAX(0,(R29+C30+E30-I30-K30)-Annahmen!C20) -> 1855.46 | Q30: =(Q29+B30+D30-H30-J30)-O30 -> 0 | R30: =(R29+C30+E30-I30-K30)-P30 -> 0 | S30: =S29+O30+P30+F30-L30 -> 102746.41 | T30: =Q30+R30+S30 -> 102746.41
A31: =DATE(YEAR(A30),MONTH(A30)+1,1) -> 46874 | B31: =Annahmen!C55 -> 4916.8605 | C31: =Annahmen!D55 -> 2605.46 | D31: =SUMIFS(Monatlich!$E$4:$E$63,Monatlich!$A$4:$A$63,"Ja",Monatlich!$H$4:$H$63,"Theo",Monatlich!$D$4:$D$63,"Einnahme",Monatlich!$J$4:$J$63,"<="&$A31,Monatlich!$K$4:$K$63,">="&$A31)+SUMIFS(Einmalig!$E$4:$E$43,Einmalig!$A$4:$A$43,"Ja",Einmalig!$G$4:$G$43,"Theo",Einmalig!$D$4:$D$43,"Einnahme",Einmalig!$I$4:$I$43,$A31) -> 0 | E31: =SUMIFS(Monatlich!$E$4:$E$63,Monatlich!$A$4:$A$63,"Ja",Monatlich!$H$4:$H$63,"Jule",Monatlich!$D$4:$D$63,"Einnahme",Monatlich!$J$4:$J$63,"<="&$A31,Monatlich!$K$4:$K$63,">="&$A31)+SUMIFS(Einmalig!$E$4:$E$43,Einmalig!$A$4:$A$43,"Ja",Einmalig!$G$4:$G$43,"Jule",Einmalig!$D$4:$D$43,"Einnahme",Einmalig!$I$4:$I$43,$A31) -> 0 | F31: =SUMIFS(Monatlich!$E$4:$E$63,Monatlich!$A$4:$A$63,"Ja",Monatlich!$H$4:$H$63,"Gemeinsam",Monatlich!$D$4:$D$63,"Einnahme",Monatlich!$J$4:$J$63,"<="&$A31,Monatlich!$K$4:$K$63,">="&$A31)+SUMIFS(Einmalig!$E$4:$E$43,Einmalig!$A$4:$A$43,"Ja",Einmalig!$G$4:$G$43,"Gemeinsam",Einmalig!$D$4:$D$43,"Einnahme",Einmalig!$I$4:$I$43,$A31) -> 0 | G31: =SUM(B31:F31) -> 7522.3205 | H31: =Annahmen!C17 -> 750 | I31: =Annahmen!C18 -> 750 | J31: =SUMIFS(Monatlich!$E$4:$E$63,Monatlich!$A$4:$A$63,"Ja",Monatlich!$H$4:$H$63,"Theo",Monatlich!$D$4:$D$63,"Ausgabe",Monatlich!$J$4:$J$63,"<="&$A31,Monatlich!$K$4:$K$63,">="&$A31)+SUMIFS(Einmalig!$E$4:$E$43,Einmalig!$A$4:$A$43,"Ja",Einmalig!$G$4:$G$43,"Theo",Einmalig!$D$4:$D$43,"Ausgabe",Einmalig!$I$4:$I$43,$A31) -> 0 | K31: =SUMIFS(Monatlich!$E$4:$E$63,Monatlich!$A$4:$A$63,"Ja",Monatlich!$H$4:$H$63,"Jule",Monatlich!$D$4:$D$63,"Ausgabe",Monatlich!$J$4:$J$63,"<="&$A31,Monatlich!$K$4:$K$63,">="&$A31)+SUMIFS(Einmalig!$E$4:$E$43,Einmalig!$A$4:$A$43,"Ja",Einmalig!$G$4:$G$43,"Jule",Einmalig!$D$4:$D$43,"Ausgabe",Einmalig!$I$4:$I$43,$A31) -> 0 | L31: =SUMIFS(Monatlich!$E$4:$E$63,Monatlich!$A$4:$A$63,"Ja",Monatlich!$H$4:$H$63,"Gemeinsam",Monatlich!$D$4:$D$63,"Ausgabe",Monatlich!$J$4:$J$63,"<="&$A31,Monatlich!$K$4:$K$63,">="&$A31)+SUMIFS(Einmalig!$E$4:$E$43,Einmalig!$A$4:$A$43,"Ja",Einmalig!$G$4:$G$43,"Gemeinsam",Einmalig!$D$4:$D$43,"Ausgabe",Einmalig!$I$4:$I$43,$A31) -> 2500 | M31: =SUM(H31:L31) -> 4000 | N31: =G31-M31 -> 3522.3205 | O31: =MAX(0,(Q30+B31+D31-H31-J31)-Annahmen!C19) -> 4166.8605 | P31: =MAX(0,(R30+C31+E31-I31-K31)-Annahmen!C20) -> 1855.46 | Q31: =(Q30+B31+D31-H31-J31)-O31 -> 0 | R31: =(R30+C31+E31-I31-K31)-P31 -> 0 | S31: =S30+O31+P31+F31-L31 -> 106268.73 | T31: =Q31+R31+S31 -> 106268.73
A32: =DATE(YEAR(A31),MONTH(A31)+1,1) -> 46905 | B32: =Annahmen!C55 -> 4916.8605 | C32: =Annahmen!D55 -> 2605.46 | D32: =SUMIFS(Monatlich!$E$4:$E$63,Monatlich!$A$4:$A$63,"Ja",Monatlich!$H$4:$H$63,"Theo",Monatlich!$D$4:$D$63,"Einnahme",Monatlich!$J$4:$J$63,"<="&$A32,Monatlich!$K$4:$K$63,">="&$A32)+SUMIFS(Einmalig!$E$4:$E$43,Einmalig!$A$4:$A$43,"Ja",Einmalig!$G$4:$G$43,"Theo",Einmalig!$D$4:$D$43,"Einnahme",Einmalig!$I$4:$I$43,$A32) -> 0 | E32: =SUMIFS(Monatlich!$E$4:$E$63,Monatlich!$A$4:$A$63,"Ja",Monatlich!$H$4:$H$63,"Jule",Monatlich!$D$4:$D$63,"Einnahme",Monatlich!$J$4:$J$63,"<="&$A32,Monatlich!$K$4:$K$63,">="&$A32)+SUMIFS(Einmalig!$E$4:$E$43,Einmalig!$A$4:$A$43,"Ja",Einmalig!$G$4:$G$43,"Jule",Einmalig!$D$4:$D$43,"Einnahme",Einmalig!$I$4:$I$43,$A32) -> 0 | F32: =SUMIFS(Monatlich!$E$4:$E$63,Monatlich!$A$4:$A$63,"Ja",Monatlich!$H$4:$H$63,"Gemeinsam",Monatlich!$D$4:$D$63,"Einnahme",Monatlich!$J$4:$J$63,"<="&$A32,Monatlich!$K$4:$K$63,">="&$A32)+SUMIFS(Einmalig!$E$4:$E$43,Einmalig!$A$4:$A$43,"Ja",Einmalig!$G$4:$G$43,"Gemeinsam",Einmalig!$D$4:$D$43,"Einnahme",Einmalig!$I$4:$I$43,$A32) -> 0 | G32: =SUM(B32:F32) -> 7522.3205 | H32: =Annahmen!C17 -> 750 | I32: =Annahmen!C18 -> 750 | J32: =SUMIFS(Monatlich!$E$4:$E$63,Monatlich!$A$4:$A$63,"Ja",Monatlich!$H$4:$H$63,"Theo",Monatlich!$D$4:$D$63,"Ausgabe",Monatlich!$J$4:$J$63,"<="&$A32,Monatlich!$K$4:$K$63,">="&$A32)+SUMIFS(Einmalig!$E$4:$E$43,Einmalig!$A$4:$A$43,"Ja",Einmalig!$G$4:$G$43,"Theo",Einmalig!$D$4:$D$43,"Ausgabe",Einmalig!$I$4:$I$43,$A32) -> 0 | K32: =SUMIFS(Monatlich!$E$4:$E$63,Monatlich!$A$4:$A$63,"Ja",Monatlich!$H$4:$H$63,"Jule",Monatlich!$D$4:$D$63,"Ausgabe",Monatlich!$J$4:$J$63,"<="&$A32,Monatlich!$K$4:$K$63,">="&$A32)+SUMIFS(Einmalig!$E$4:$E$43,Einmalig!$A$4:$A$43,"Ja",Einmalig!$G$4:$G$43,"Jule",Einmalig!$D$4:$D$43,"Ausgabe",Einmalig!$I$4:$I$43,$A32) -> 0 | L32: =SUMIFS(Monatlich!$E$4:$E$63,Monatlich!$A$4:$A$63,"Ja",Monatlich!$H$4:$H$63,"Gemeinsam",Monatlich!$D$4:$D$63,"Ausgabe",Monatlich!$J$4:$J$63,"<="&$A32,Monatlich!$K$4:$K$63,">="&$A32)+SUMIFS(Einmalig!$E$4:$E$43,Einmalig!$A$4:$A$43,"Ja",Einmalig!$G$4:$G$43,"Gemeinsam",Einmalig!$D$4:$D$43,"Ausgabe",Einmalig!$I$4:$I$43,$A32) -> 2500 | M32: =SUM(H32:L32) -> 4000 | N32: =G32-M32 -> 3522.3205 | O32: =MAX(0,(Q31+B32+D32-H32-J32)-Annahmen!C19) -> 4166.8605 | P32: =MAX(0,(R31+C32+E32-I32-K32)-Annahmen!C20) -> 1855.46 | Q32: =(Q31+B32+D32-H32-J32)-O32 -> 0 | R32: =(R31+C32+E32-I32-K32)-P32 -> 0 | S32: =S31+O32+P32+F32-L32 -> 109791.05 | T32: =Q32+R32+S32 -> 109791.05
A33: =DATE(YEAR(A32),MONTH(A32)+1,1) -> 46935 | B33: =Annahmen!C55 -> 4916.8605 | C33: =Annahmen!D55 -> 2605.46 | D33: =SUMIFS(Monatlich!$E$4:$E$63,Monatlich!$A$4:$A$63,"Ja",Monatlich!$H$4:$H$63,"Theo",Monatlich!$D$4:$D$63,"Einnahme",Monatlich!$J$4:$J$63,"<="&$A33,Monatlich!$K$4:$K$63,">="&$A33)+SUMIFS(Einmalig!$E$4:$E$43,Einmalig!$A$4:$A$43,"Ja",Einmalig!$G$4:$G$43,"Theo",Einmalig!$D$4:$D$43,"Einnahme",Einmalig!$I$4:$I$43,$A33) -> 0 | E33: =SUMIFS(Monatlich!$E$4:$E$63,Monatlich!$A$4:$A$63,"Ja",Monatlich!$H$4:$H$63,"Jule",Monatlich!$D$4:$D$63,"Einnahme",Monatlich!$J$4:$J$63,"<="&$A33,Monatlich!$K$4:$K$63,">="&$A33)+SUMIFS(Einmalig!$E$4:$E$43,Einmalig!$A$4:$A$43,"Ja",Einmalig!$G$4:$G$43,"Jule",Einmalig!$D$4:$D$43,"Einnahme",Einmalig!$I$4:$I$43,$A33) -> 0 | F33: =SUMIFS(Monatlich!$E$4:$E$63,Monatlich!$A$4:$A$63,"Ja",Monatlich!$H$4:$H$63,"Gemeinsam",Monatlich!$D$4:$D$63,"Einnahme",Monatlich!$J$4:$J$63,"<="&$A33,Monatlich!$K$4:$K$63,">="&$A33)+SUMIFS(Einmalig!$E$4:$E$43,Einmalig!$A$4:$A$43,"Ja",Einmalig!$G$4:$G$43,"Gemeinsam",Einmalig!$D$4:$D$43,"Einnahme",Einmalig!$I$4:$I$43,$A33) -> 0 | G33: =SUM(B33:F33) -> 7522.3205 | H33: =Annahmen!C17 -> 750 | I33: =Annahmen!C18 -> 750 | J33: =SUMIFS(Monatlich!$E$4:$E$63,Monatlich!$A$4:$A$63,"Ja",Monatlich!$H$4:$H$63,"Theo",Monatlich!$D$4:$D$63,"Ausgabe",Monatlich!$J$4:$J$63,"<="&$A33,Monatlich!$K$4:$K$63,">="&$A33)+SUMIFS(Einmalig!$E$4:$E$43,Einmalig!$A$4:$A$43,"Ja",Einmalig!$G$4:$G$43,"Theo",Einmalig!$D$4:$D$43,"Ausgabe",Einmalig!$I$4:$I$43,$A33) -> 0 | K33: =SUMIFS(Monatlich!$E$4:$E$63,Monatlich!$A$4:$A$63,"Ja",Monatlich!$H$4:$H$63,"Jule",Monatlich!$D$4:$D$63,"Ausgabe",Monatlich!$J$4:$J$63,"<="&$A33,Monatlich!$K$4:$K$63,">="&$A33)+SUMIFS(Einmalig!$E$4:$E$43,Einmalig!$A$4:$A$43,"Ja",Einmalig!$G$4:$G$43,"Jule",Einmalig!$D$4:$D$43,"Ausgabe",Einmalig!$I$4:$I$43,$A33) -> 0 | L33: =SUMIFS(Monatlich!$E$4:$E$63,Monatlich!$A$4:$A$63,"Ja",Monatlich!$H$4:$H$63,"Gemeinsam",Monatlich!$D$4:$D$63,"Ausgabe",Monatlich!$J$4:$J$63,"<="&$A33,Monatlich!$K$4:$K$63,">="&$A33)+SUMIFS(Einmalig!$E$4:$E$43,Einmalig!$A$4:$A$43,"Ja",Einmalig!$G$4:$G$43,"Gemeinsam",Einmalig!$D$4:$D$43,"Ausgabe",Einmalig!$I$4:$I$43,$A33) -> 2500 | M33: =SUM(H33:L33) -> 4000 | N33: =G33-M33 -> 3522.3205 | O33: =MAX(0,(Q32+B33+D33-H33-J33)-Annahmen!C19) -> 4166.8605 | P33: =MAX(0,(R32+C33+E33-I33-K33)-Annahmen!C20) -> 1855.46 | Q33: =(Q32+B33+D33-H33-J33)-O33 -> 0 | R33: =(R32+C33+E33-I33-K33)-P33 -> 0 | S33: =S32+O33+P33+F33-L33 -> 113313.37 | T33: =Q33+R33+S33 -> 113313.37
A34: =DATE(YEAR(A33),MONTH(A33)+1,1) -> 46966 | B34: =Annahmen!C55 -> 4916.8605 | C34: =Annahmen!D55 -> 2605.46 | D34: =SUMIFS(Monatlich!$E$4:$E$63,Monatlich!$A$4:$A$63,"Ja",Monatlich!$H$4:$H$63,"Theo",Monatlich!$D$4:$D$63,"Einnahme",Monatlich!$J$4:$J$63,"<="&$A34,Monatlich!$K$4:$K$63,">="&$A34)+SUMIFS(Einmalig!$E$4:$E$43,Einmalig!$A$4:$A$43,"Ja",Einmalig!$G$4:$G$43,"Theo",Einmalig!$D$4:$D$43,"Einnahme",Einmalig!$I$4:$I$43,$A34) -> 0 | E34: =SUMIFS(Monatlich!$E$4:$E$63,Monatlich!$A$4:$A$63,"Ja",Monatlich!$H$4:$H$63,"Jule",Monatlich!$D$4:$D$63,"Einnahme",Monatlich!$J$4:$J$63,"<="&$A34,Monatlich!$K$4:$K$63,">="&$A34)+SUMIFS(Einmalig!$E$4:$E$43,Einmalig!$A$4:$A$43,"Ja",Einmalig!$G$4:$G$43,"Jule",Einmalig!$D$4:$D$43,"Einnahme",Einmalig!$I$4:$I$43,$A34) -> 0 | F34: =SUMIFS(Monatlich!$E$4:$E$63,Monatlich!$A$4:$A$63,"Ja",Monatlich!$H$4:$H$63,"Gemeinsam",Monatlich!$D$4:$D$63,"Einnahme",Monatlich!$J$4:$J$63,"<="&$A34,Monatlich!$K$4:$K$63,">="&$A34)+SUMIFS(Einmalig!$E$4:$E$43,Einmalig!$A$4:$A$43,"Ja",Einmalig!$G$4:$G$43,"Gemeinsam",Einmalig!$D$4:$D$43,"Einnahme",Einmalig!$I$4:$I$43,$A34) -> 0 | G34: =SUM(B34:F34) -> 7522.3205 | H34: =Annahmen!C17 -> 750 | I34: =Annahmen!C18 -> 750 | J34: =SUMIFS(Monatlich!$E$4:$E$63,Monatlich!$A$4:$A$63,"Ja",Monatlich!$H$4:$H$63,"Theo",Monatlich!$D$4:$D$63,"Ausgabe",Monatlich!$J$4:$J$63,"<="&$A34,Monatlich!$K$4:$K$63,">="&$A34)+SUMIFS(Einmalig!$E$4:$E$43,Einmalig!$A$4:$A$43,"Ja",Einmalig!$G$4:$G$43,"Theo",Einmalig!$D$4:$D$43,"Ausgabe",Einmalig!$I$4:$I$43,$A34) -> 0 | K34: =SUMIFS(Monatlich!$E$4:$E$63,Monatlich!$A$4:$A$63,"Ja",Monatlich!$H$4:$H$63,"Jule",Monatlich!$D$4:$D$63,"Ausgabe",Monatlich!$J$4:$J$63,"<="&$A34,Monatlich!$K$4:$K$63,">="&$A34)+SUMIFS(Einmalig!$E$4:$E$43,Einmalig!$A$4:$A$43,"Ja",Einmalig!$G$4:$G$43,"Jule",Einmalig!$D$4:$D$43,"Ausgabe",Einmalig!$I$4:$I$43,$A34) -> 0 | L34: =SUMIFS(Monatlich!$E$4:$E$63,Monatlich!$A$4:$A$63,"Ja",Monatlich!$H$4:$H$63,"Gemeinsam",Monatlich!$D$4:$D$63,"Ausgabe",Monatlich!$J$4:$J$63,"<="&$A34,Monatlich!$K$4:$K$63,">="&$A34)+SUMIFS(Einmalig!$E$4:$E$43,Einmalig!$A$4:$A$43,"Ja",Einmalig!$G$4:$G$43,"Gemeinsam",Einmalig!$D$4:$D$43,"Ausgabe",Einmalig!$I$4:$I$43,$A34) -> 2500 | M34: =SUM(H34:L34) -> 4000 | N34: =G34-M34 -> 3522.3205 | O34: =MAX(0,(Q33+B34+D34-H34-J34)-Annahmen!C19) -> 4166.8605 | P34: =MAX(0,(R33+C34+E34-I34-K34)-Annahmen!C20) -> 1855.46 | Q34: =(Q33+B34+D34-H34-J34)-O34 -> 0 | R34: =(R33+C34+E34-I34-K34)-P34 -> 0 | S34: =S33+O34+P34+F34-L34 -> 116835.69 | T34: =Q34+R34+S34 -> 116835.69
A36: Lesehilfe: „Budget Theo/Jule“ ist das persönliche Geld, das auf dem Privatkonto bleibt und dort ausgegeben wird. „→ Gemeinsam“ ist der Betrag, der vom Privatkonto auf das gemeinsame Konto geht – er fließt erst, wenn das Privatkonto den in den Annahmen gesetzten Zielsaldo erreicht hat. Deshalb wird Theos Minus zuerst ausgeglichen.

Sheet Annahmen
A1: Annahmen & Parameter
A2: Alle blau/gelb hinterlegten Zellen sind Eingaben – hier darfst du rechnen und aendern. Schwarze Werte sind Formeln. Stand der Steuer- und SV-Werte: 2026.
A4: 1 · Planung
A5: Planungsstart (erster Monat) | C5: 46266 | H5: Das Monatsraster im Blatt „Übersicht“ ist auf 24 Monate ausgelegt.
A6: Planungshorizont (Monate) | C6: 24
A7: Sparziel | C7: 35000 | H7: Angabe von dir: 35.000 € bis Juli 2027.
A8: Zielmonat für das Sparziel | C8: 46569
A10: 2 · Startsalden (Stand heute)
A11: Konto Theo | C11: -4000 | H11: Angaben von dir.
A12: Konto Jule | C12: 500
A13: Konto Gemeinsam | C13: 0
A14: Summe | C14: =C11+C12+C13 -> -3500
A16: 3 · Kontoregel: was auf den Privatkonten bleibt
A17: Persönliches Budget Theo / Monat | C17: 750
A18: Persönliches Budget Jule / Monat | C18: 750
A19: Zielsaldo Privatkonto Theo | C19: 0
A20: Zielsaldo Privatkonto Jule | C20: 0
A21: Regel im Modell: Gehalt geht auf das jeweilige Privatkonto. Davon bleibt das persönliche Budget stehen (wird ausgegeben); der Rest wird auf „Gemeinsam“ überwiesen – aber erst, wenn das Privatkonto den Zielsaldo erreicht hat. Theos −4.000 € werden dadurch automatisch zuerst ausgeglichen.
A24: 4 · Sozialversicherung 2026 – Arbeitnehmeranteile
A25: Beitrag | C25: Satz | H25: Hinweis
A26: Krankenversicherung | C26: 0.0875 | H26: 7,30 % + halber Zusatzbeitrag (Ø 2,90 % in 2026)
A27: Pflegeversicherung | C27: 0.024 | H27: 1,80 % + 0,60 % Zuschlag für Kinderlose ab 23
A28: Rentenversicherung | C28: 0.093 | H28: halber Beitragssatz von 18,60 %
A29: Arbeitslosenversicherung | C29: 0.013 | H29: halber Beitragssatz von 2,60 %
A30: Beitragsbemessungsgrenze KV/PV (Monat) | C30: 5812.5 | H30: 69.750 € pro Jahr
A31: Beitragsbemessungsgrenze RV/AV (Monat) | C31: 8450 | H31: 101.400 € pro Jahr
A33: 5 · Bruttogehälter
A34: TV-AVH Entgeltgruppe 13, Stufe 1 (Vollzeit / Monat) | C34: 4901.11 | H34: Tabelle TV-AVH, gültig ab 01.05.2026. Stufe im Vertrag nicht genannt – bitte in der Abrechnung prüfen (Referenztabelle unten).
A35: Teilzeitquote laut Arbeitsvertrag | C35: 0.75 | H35: § 3 des DESY-Vertrags: Teilzeit mit 75 v. H.
B37: Theo · Hauptjob | C37: Theo · DESY (Promotion) | D37: Jule
A38: Steuerklasse | B38: I | C38: VI | D38: I | H38: Zweitjob wird zwingend nach Steuerklasse VI abgerechnet.
A39: Monatsbrutto | B39: =B40/12 -> 4166.6667 | C39: =$C34*$C35 -> 3675.8325 | D39: =D40/12 -> 4000
A40: Jahresbrutto | B40: 50000 | C40: =C39*12 -> 44109.99 | D40: 48000 | H40: Angaben von dir: 50.000 € bzw. 48.000 €. DESY ergibt sich aus Tarif × Quote.
A42: 6 · Vom Brutto zum Netto (pro Monat)
C43: Theo (beide Jobs) | D43: Jule
A44: Bruttogehalt gesamt | C44: =B39+C39 -> 7842.4992 | D44: =D39 -> 4000
A45: Bemessungsgrundlage KV / PV | C45: =MIN(C44,$C30) -> 5812.5 | D45: =MIN(D44,$C30) -> 4000 | H45: Bei zwei Jobs zählt das Gesamtbrutto – die Beitragsbemessungsgrenze wirkt nur einmal (§ 22 SGB IV). Das spart Theo rund 226 € im Monat.
A46: Bemessungsgrundlage RV / AV | C46: =MIN(C44,$C31) -> 7842.4992 | D46: =MIN(D44,$C31) -> 4000
A47: − Krankenversicherung | C47: =-C45*$C26 -> -508.59375 | D47: =-D45*$C26 -> -350
A48: − Pflegeversicherung | C48: =-C45*$C27 -> -139.5 | D48: =-D45*$C27 -> -96
A49: − Rentenversicherung | C49: =-C46*$C28 -> -729.35242 | D49: =-D46*$C28 -> -372
A50: − Arbeitslosenversicherung | C50: =-C46*$C29 -> -101.95249 | D50: =-D46*$C29 -> -52
A51: − Lohnsteuer Hauptjob (StKl I) | C51: -565.69 | D51: -524.54 | H51: Schätzung nach Steuertarif 2026 – bitte mit der Abrechnung abgleichen.
A52: − Lohnsteuer Nebenjob (StKl VI) | C52: -880.55 | D52: 0
A53: − Solidaritätszuschlag | C53: 0 | D53: 0 | H53: Freigrenze wird beim monatlichen Abzug nicht überschritten.
A54: − Kirchensteuer | C54: 0 | D54: 0 | H54: Annahme: keine Kirchensteuer. Falls doch, hier 9 % der Lohnsteuer eintragen.
A55: =NETTO pro Monat -> #NAME? | C55: =C44+SUM(C47:C54) -> 4916.8605 | D55: =D44+SUM(D47:D54) -> 2605.46
A56: Netto Haushalt pro Monat | C56: =C55+D55 -> 7522.3205
A58: 7 · Referenz: TV-AVH Entgeltgruppe 13, gültig ab 01.05.2026 (Vollzeit / Monat)
B59: Stufe 1 | C59: Stufe 2 | D59: Stufe 3 | E59: Stufe 4 | F59: Stufe 5 | G59: Stufe 6
A60: Entgeltgruppe 13 | B60: 4901.11 | C60: 5279.32 | D60: 5709.87 | E60: 6177.31 | F60: 6727.38 | G60: 6919.54
A61: Quelle: Arbeitsrechtliche Vereinigung Hamburg e. V., Anlage A zum TV-AVH, Fassung ÄTV Nr. 22 vom 06.04.2025, Tabelle gültig ab 01.05.2026. 75 % davon ergibt Theos DESY-Brutto.
A63: 8 · Hinweise, Annahmen und Quellen
A64: • Arbeitsvertrag DESY (gelesen): Beginn 16.03.2026, befristet bis 15.03.2029 nach WissZeitVG, Tätigkeit Doktorand:in in Hamburg, Teilzeit 75 v. H., Entgeltgruppe 13 TV-AVH, sechs Monate Probezeit.
A65: • Die Stufe innerhalb der Entgeltgruppe steht nicht im Vertrag. Das Modell rechnet mit Stufe 1 – der übliche Einstieg. Steht in deiner Abrechnung eine andere Stufe, oben den Vollzeitbetrag austauschen.
A66: • Theos Zweitjob läuft zwingend in Steuerklasse VI. Deshalb bleibt vom DESY-Brutto deutlich weniger übrig, als eine einfache Netto-Rechnung vermuten lässt.
A67: • Weil beide Jobs zusammen über der Beitragsbemessungsgrenze der Kranken- und Pflegeversicherung liegen, werden KV und PV nur bis 5.812,50 € berechnet. Falls ein Arbeitgeber das nicht berücksichtigt, holst du die zu viel gezahlten Beiträge über einen Erstattungsantrag bei der Krankenkasse zurück.
A68: • Steuernachzahlung: Steuerklasse I + VI führen zusammen zu weniger Abzug, als die Jahressteuer verlangt. Überschlägig fehlen bei vollem Jahr rund 3.700 € – als Einmalposten im Blatt „Einmalig“ hinterlegt.
A69: • Der Founder Secondary ist dort brutto eingetragen. Die Steuer darauf hängt an der Struktur: bei mindestens 1 % Beteiligung Teileinkünfteverfahren nach § 17 EStG, sonst Abgeltungsteuer. Beides landet grob bei einem Viertel des Gewinns – als eigener Posten hinterlegt und unbedingt mit dem Steuerberater zu prüfen.
A70: • Steuer- und Sozialversicherungswerte 2026: Grundfreibetrag 12.348 €, Tarif nach § 32a EStG in der ab 2026 geltenden Fassung, durchschnittlicher Zusatzbeitrag 2,9 %, Pflegeversicherung 3,6 % plus 0,6 % für Kinderlose.
A71: • Nicht enthalten: Kirchensteuer, Kinderfreibeträge, vermögenswirksame Leistungen, betriebliche Altersvorsorge über den Tarifvertrag hinaus, Zinsen auf Guthaben und Dispozinsen.

Sheet Monatlich
A1: Monatliche Posten
A2: Jede Zeile ist ein wiederkehrender Posten. „Aktiv = Nein“ schaltet ihn aus, ohne ihn zu löschen. „Von“ leer = ab Planungsstart, „Bis“ leer = unbefristet. Die grauen Spalten J und K rechnen intern und sollten nicht überschrieben werden.
A3: Aktiv | B3: Bezeichnung | C3: Kategorie | D3: Typ | E3: Betrag / Monat | F3: Von (Monat) | G3: Bis (Monat) | H3: Konto | I3: Notiz | J3: Von·intern | K3: Bis·intern
A4: Ja | B4: Miete Wohnung | C4: Wohnen | D4: Ausgabe | E4: 1000 | F4: 46266 | H4: Gemeinsam | I4: Angabe von dir: 1.000 € pro Monat. | J4: =IF($B4="","",IF($F4="",Annahmen!$C5,DATE(YEAR($F4),MONTH($F4),1))) -> 46266 | K4: =IF($B4="","",IF($G4="",DATE(2099,12,31),DATE(YEAR($G4),MONTH($G4),1))) -> 73050
A5: Ja | B5: Haushalt (Lebensmittel, Strom, Internet, Alltag) | C5: Haushalt | D5: Ausgabe | E5: 1500 | F5: 46266 | H5: Gemeinsam | I5: Angabe von dir: rund 1.500 € pro Monat. | J5: =IF($B5="","",IF($F5="",Annahmen!$C5,DATE(YEAR($F5),MONTH($F5),1))) -> 46266 | K5: =IF($B5="","",IF($G5="",DATE(2099,12,31),DATE(YEAR($G5),MONTH($G5),1))) -> 73050
A6: Nein | B6: Versicherungen | C6: Versicherung | D6: Ausgabe | E6: 0 | F6: 46266 | H6: Gemeinsam | I6: Beispielzeile – Betrag eintragen und auf „Ja“ stellen. | J6: =IF($B6="","",IF($F6="",Annahmen!$C5,DATE(YEAR($F6),MONTH($F6),1))) -> 46266 | K6: =IF($B6="","",IF($G6="",DATE(2099,12,31),DATE(YEAR($G6),MONTH($G6),1))) -> 73050
A7: Nein | B7: Mobilfunk & Abos | C7: Abos | D7: Ausgabe | E7: 0 | F7: 46266 | H7: Gemeinsam | I7: Beispielzeile. | J7: =IF($B7="","",IF($F7="",Annahmen!$C5,DATE(YEAR($F7),MONTH($F7),1))) -> 46266 | K7: =IF($B7="","",IF($G7="",DATE(2099,12,31),DATE(YEAR($G7),MONTH($G7),1))) -> 73050
A8: Nein | B8: Mobilität (Auto, Deutschlandticket) | C8: Mobilität | D8: Ausgabe | E8: 0 | F8: 46266 | H8: Gemeinsam | I8: Beispielzeile. | J8: =IF($B8="","",IF($F8="",Annahmen!$C5,DATE(YEAR($F8),MONTH($F8),1))) -> 46266 | K8: =IF($B8="","",IF($G8="",DATE(2099,12,31),DATE(YEAR($G8),MONTH($G8),1))) -> 73050
A9: Nein | B9: Einkommensteuer-Vorauszahlung Theo | C9: Steuern | D9: Ausgabe | E9: 305 | F9: 46722 | H9: Gemeinsam | I9: Sehr wahrscheinlich setzt das Finanzamt nach dem ersten Bescheid Vorauszahlungen fest. Dann hier aktivieren und den Einmalposten entsprechend kürzen. | J9: =IF($B9="","",IF($F9="",Annahmen!$C5,DATE(YEAR($F9),MONTH($F9),1))) -> 46722 | K9: =IF($B9="","",IF($G9="",DATE(2099,12,31),DATE(YEAR($G9),MONTH($G9),1))) -> 73050
A10: Nein | B10: Zusatzeinkommen / Nebentätigkeit | C10: Einkommen | D10: Einnahme | E10: 0 | F10: 46266 | H10: Theo | I10: Beispielzeile für wiederkehrende Einnahmen. | J10: =IF($B10="","",IF($F10="",Annahmen!$C5,DATE(YEAR($F10),MONTH($F10),1))) -> 46266 | K10: =IF($B10="","",IF($G10="",DATE(2099,12,31),DATE(YEAR($G10),MONTH($G10),1))) -> 73050
J11: =IF($B11="","",IF($F11="",Annahmen!$C5,DATE(YEAR($F11),MONTH($F11),1))) | K11: =IF($B11="","",IF($G11="",DATE(2099,12,31),DATE(YEAR($G11),MONTH($G11),1)))
J12: =IF($B12="","",IF($F12="",Annahmen!$C5,DATE(YEAR($F12),MONTH($F12),1))) | K12: =IF($B12="","",IF($G12="",DATE(2099,12,31),DATE(YEAR($G12),MONTH($G12),1)))
J13: =IF($B13="","",IF($F13="",Annahmen!$C5,DATE(YEAR($F13),MONTH($F13),1))) | K13: =IF($B13="","",IF($G13="",DATE(2099,12,31),DATE(YEAR($G13),MONTH($G13),1)))
J14: =IF($B14="","",IF($F14="",Annahmen!$C5,DATE(YEAR($F14),MONTH($F14),1))) | K14: =IF($B14="","",IF($G14="",DATE(2099,12,31),DATE(YEAR($G14),MONTH($G14),1)))
J15: =IF($B15="","",IF($F15="",Annahmen!$C5,DATE(YEAR($F15),MONTH($F15),1))) | K15: =IF($B15="","",IF($G15="",DATE(2099,12,31),DATE(YEAR($G15),MONTH($G15),1)))
J16: =IF($B16="","",IF($F16="",Annahmen!$C5,DATE(YEAR($F16),MONTH($F16),1))) | K16: =IF($B16="","",IF($G16="",DATE(2099,12,31),DATE(YEAR($G16),MONTH($G16),1)))
J17: =IF($B17="","",IF($F17="",Annahmen!$C5,DATE(YEAR($F17),MONTH($F17),1))) | K17: =IF($B17="","",IF($G17="",DATE(2099,12,31),DATE(YEAR($G17),MONTH($G17),1)))
J18: =IF($B18="","",IF($F18="",Annahmen!$C5,DATE(YEAR($F18),MONTH($F18),1))) | K18: =IF($B18="","",IF($G18="",DATE(2099,12,31),DATE(YEAR($G18),MONTH($G18),1)))
J19: =IF($B19="","",IF($F19="",Annahmen!$C5,DATE(YEAR($F19),MONTH($F19),1))) | K19: =IF($B19="","",IF($G19="",DATE(2099,12,31),DATE(YEAR($G19),MONTH($G19),1)))
J20: =IF($B20="","",IF($F20="",Annahmen!$C5,DATE(YEAR($F20),MONTH($F20),1))) | K20: =IF($B20="","",IF($G20="",DATE(2099,12,31),DATE(YEAR($G20),MONTH($G20),1)))
J21: =IF($B21="","",IF($F21="",Annahmen!$C5,DATE(YEAR($F21),MONTH($F21),1))) | K21: =IF($B21="","",IF($G21="",DATE(2099,12,31),DATE(YEAR($G21),MONTH($G21),1)))
J22: =IF($B22="","",IF($F22="",Annahmen!$C5,DATE(YEAR($F22),MONTH($F22),1))) | K22: =IF($B22="","",IF($G22="",DATE(2099,12,31),DATE(YEAR($G22),MONTH($G22),1)))
J23: =IF($B23="","",IF($F23="",Annahmen!$C5,DATE(YEAR($F23),MONTH($F23),1))) | K23: =IF($B23="","",IF($G23="",DATE(2099,12,31),DATE(YEAR($G23),MONTH($G23),1)))
J24: =IF($B24="","",IF($F24="",Annahmen!$C5,DATE(YEAR($F24),MONTH($F24),1))) | K24: =IF($B24="","",IF($G24="",DATE(2099,12,31),DATE(YEAR($G24),MONTH($G24),1)))
J25: =IF($B25="","",IF($F25="",Annahmen!$C5,DATE(YEAR($F25),MONTH($F25),1))) | K25: =IF($B25="","",IF($G25="",DATE(2099,12,31),DATE(YEAR($G25),MONTH($G25),1)))
J26: =IF($B26="","",IF($F26="",Annahmen!$C5,DATE(YEAR($F26),MONTH($F26),1))) | K26: =IF($B26="","",IF($G26="",DATE(2099,12,31),DATE(YEAR($G26),MONTH($G26),1)))
J27: =IF($B27="","",IF($F27="",Annahmen!$C5,DATE(YEAR($F27),MONTH($F27),1))) | K27: =IF($B27="","",IF($G27="",DATE(2099,12,31),DATE(YEAR($G27),MONTH($G27),1)))
J28: =IF($B28="","",IF($F28="",Annahmen!$C5,DATE(YEAR($F28),MONTH($F28),1))) | K28: =IF($B28="","",IF($G28="",DATE(2099,12,31),DATE(YEAR($G28),MONTH($G28),1)))
J29: =IF($B29="","",IF($F29="",Annahmen!$C5,DATE(YEAR($F29),MONTH($F29),1))) | K29: =IF($B29="","",IF($G29="",DATE(2099,12,31),DATE(YEAR($G29),MONTH($G29),1)))
J30: =IF($B30="","",IF($F30="",Annahmen!$C5,DATE(YEAR($F30),MONTH($F30),1))) | K30: =IF($B30="","",IF($G30="",DATE(2099,12,31),DATE(YEAR($G30),MONTH($G30),1)))
J31: =IF($B31="","",IF($F31="",Annahmen!$C5,DATE(YEAR($F31),MONTH($F31),1))) | K31: =IF($B31="","",IF($G31="",DATE(2099,12,31),DATE(YEAR($G31),MONTH($G31),1)))
J32: =IF($B32="","",IF($F32="",Annahmen!$C5,DATE(YEAR($F32),MONTH($F32),1))) | K32: =IF($B32="","",IF($G32="",DATE(2099,12,31),DATE(YEAR($G32),MONTH($G32),1)))
J33: =IF($B33="","",IF($F33="",Annahmen!$C5,DATE(YEAR($F33),MONTH($F33),1))) | K33: =IF($B33="","",IF($G33="",DATE(2099,12,31),DATE(YEAR($G33),MONTH($G33),1)))
J34: =IF($B34="","",IF($F34="",Annahmen!$C5,DATE(YEAR($F34),MONTH($F34),1))) | K34: =IF($B34="","",IF($G34="",DATE(2099,12,31),DATE(YEAR($G34),MONTH($G34),1)))
J35: =IF($B35="","",IF($F35="",Annahmen!$C5,DATE(YEAR($F35),MONTH($F35),1))) | K35: =IF($B35="","",IF($G35="",DATE(2099,12,31),DATE(YEAR($G35),MONTH($G35),1)))
J36: =IF($B36="","",IF($F36="",Annahmen!$C5,DATE(YEAR($F36),MONTH($F36),1))) | K36: =IF($B36="","",IF($G36="",DATE(2099,12,31),DATE(YEAR($G36),MONTH($G36),1)))
J37: =IF($B37="","",IF($F37="",Annahmen!$C5,DATE(YEAR($F37),MONTH($F37),1))) | K37: =IF($B37="","",IF($G37="",DATE(2099,12,31),DATE(YEAR($G37),MONTH($G37),1)))
J38: =IF($B38="","",IF($F38="",Annahmen!$C5,DATE(YEAR($F38),MONTH($F38),1))) | K38: =IF($B38="","",IF($G38="",DATE(2099,12,31),DATE(YEAR($G38),MONTH($G38),1)))
J39: =IF($B39="","",IF($F39="",Annahmen!$C5,DATE(YEAR($F39),MONTH($F39),1))) | K39: =IF($B39="","",IF($G39="",DATE(2099,12,31),DATE(YEAR($G39),MONTH($G39),1)))
J40: =IF($B40="","",IF($F40="",Annahmen!$C5,DATE(YEAR($F40),MONTH($F40),1))) | K40: =IF($B40="","",IF($G40="",DATE(2099,12,31),DATE(YEAR($G40),MONTH($G40),1)))
J41: =IF($B41="","",IF($F41="",Annahmen!$C5,DATE(YEAR($F41),MONTH($F41),1))) | K41: =IF($B41="","",IF($G41="",DATE(2099,12,31),DATE(YEAR($G41),MONTH($G41),1)))
J42: =IF($B42="","",IF($F42="",Annahmen!$C5,DATE(YEAR($F42),MONTH($F42),1))) | K42: =IF($B42="","",IF($G42="",DATE(2099,12,31),DATE(YEAR($G42),MONTH($G42),1)))
J43: =IF($B43="","",IF($F43="",Annahmen!$C5,DATE(YEAR($F43),MONTH($F43),1))) | K43: =IF($B43="","",IF($G43="",DATE(2099,12,31),DATE(YEAR($G43),MONTH($G43),1)))
J44: =IF($B44="","",IF($F44="",Annahmen!$C5,DATE(YEAR($F44),MONTH($F44),1))) | K44: =IF($B44="","",IF($G44="",DATE(2099,12,31),DATE(YEAR($G44),MONTH($G44),1)))
J45: =IF($B45="","",IF($F45="",Annahmen!$C5,DATE(YEAR($F45),MONTH($F45),1))) | K45: =IF($B45="","",IF($G45="",DATE(2099,12,31),DATE(YEAR($G45),MONTH($G45),1)))
J46: =IF($B46="","",IF($F46="",Annahmen!$C5,DATE(YEAR($F46),MONTH($F46),1))) | K46: =IF($B46="","",IF($G46="",DATE(2099,12,31),DATE(YEAR($G46),MONTH($G46),1)))
J47: =IF($B47="","",IF($F47="",Annahmen!$C5,DATE(YEAR($F47),MONTH($F47),1))) | K47: =IF($B47="","",IF($G47="",DATE(2099,12,31),DATE(YEAR($G47),MONTH($G47),1)))
J48: =IF($B48="","",IF($F48="",Annahmen!$C5,DATE(YEAR($F48),MONTH($F48),1))) | K48: =IF($B48="","",IF($G48="",DATE(2099,12,31),DATE(YEAR($G48),MONTH($G48),1)))
J49: =IF($B49="","",IF($F49="",Annahmen!$C5,DATE(YEAR($F49),MONTH($F49),1))) | K49: =IF($B49="","",IF($G49="",DATE(2099,12,31),DATE(YEAR($G49),MONTH($G49),1)))
J50: =IF($B50="","",IF($F50="",Annahmen!$C5,DATE(YEAR($F50),MONTH($F50),1))) | K50: =IF($B50="","",IF($G50="",DATE(2099,12,31),DATE(YEAR($G50),MONTH($G50),1)))
J51: =IF($B51="","",IF($F51="",Annahmen!$C5,DATE(YEAR($F51),MONTH($F51),1))) | K51: =IF($B51="","",IF($G51="",DATE(2099,12,31),DATE(YEAR($G51),MONTH($G51),1)))
J52: =IF($B52="","",IF($F52="",Annahmen!$C5,DATE(YEAR($F52),MONTH($F52),1))) | K52: =IF($B52="","",IF($G52="",DATE(2099,12,31),DATE(YEAR($G52),MONTH($G52),1)))
J53: =IF($B53="","",IF($F53="",Annahmen!$C5,DATE(YEAR($F53),MONTH($F53),1))) | K53: =IF($B53="","",IF($G53="",DATE(2099,12,31),DATE(YEAR($G53),MONTH($G53),1)))
J54: =IF($B54="","",IF($F54="",Annahmen!$C5,DATE(YEAR($F54),MONTH($F54),1))) | K54: =IF($B54="","",IF($G54="",DATE(2099,12,31),DATE(YEAR($G54),MONTH($G54),1)))
J55: =IF($B55="","",IF($F55="",Annahmen!$C5,DATE(YEAR($F55),MONTH($F55),1))) | K55: =IF($B55="","",IF($G55="",DATE(2099,12,31),DATE(YEAR($G55),MONTH($G55),1)))
J56: =IF($B56="","",IF($F56="",Annahmen!$C5,DATE(YEAR($F56),MONTH($F56),1))) | K56: =IF($B56="","",IF($G56="",DATE(2099,12,31),DATE(YEAR($G56),MONTH($G56),1)))
J57: =IF($B57="","",IF($F57="",Annahmen!$C5,DATE(YEAR($F57),MONTH($F57),1))) | K57: =IF($B57="","",IF($G57="",DATE(2099,12,31),DATE(YEAR($G57),MONTH($G57),1)))
J58: =IF($B58="","",IF($F58="",Annahmen!$C5,DATE(YEAR($F58),MONTH($F58),1))) | K58: =IF($B58="","",IF($G58="",DATE(2099,12,31),DATE(YEAR($G58),MONTH($G58),1)))
J59: =IF($B59="","",IF($F59="",Annahmen!$C5,DATE(YEAR($F59),MONTH($F59),1))) | K59: =IF($B59="","",IF($G59="",DATE(2099,12,31),DATE(YEAR($G59),MONTH($G59),1)))
J60: =IF($B60="","",IF($F60="",Annahmen!$C5,DATE(YEAR($F60),MONTH($F60),1))) | K60: =IF($B60="","",IF($G60="",DATE(2099,12,31),DATE(YEAR($G60),MONTH($G60),1)))
J61: =IF($B61="","",IF($F61="",Annahmen!$C5,DATE(YEAR($F61),MONTH($F61),1))) | K61: =IF($B61="","",IF($G61="",DATE(2099,12,31),DATE(YEAR($G61),MONTH($G61),1)))
J62: =IF($B62="","",IF($F62="",Annahmen!$C5,DATE(YEAR($F62),MONTH($F62),1))) | K62: =IF($B62="","",IF($G62="",DATE(2099,12,31),DATE(YEAR($G62),MONTH($G62),1)))
J63: =IF($B63="","",IF($F63="",Annahmen!$C5,DATE(YEAR($F63),MONTH($F63),1))) | K63: =IF($B63="","",IF($G63="",DATE(2099,12,31),DATE(YEAR($G63),MONTH($G63),1)))

Sheet Einmalig
A1: Einmalzahlungen
A2: Einzelne Zahlungen, die genau in einem Monat anfallen – Hochzeit, Urlaub, Bonus, Steuerbescheid. „Aktiv = Nein“ schaltet den Posten aus. Spalte I rechnet intern.
A3: Aktiv | B3: Bezeichnung | C3: Kategorie | D3: Typ | E3: Betrag | F3: Monat | G3: Konto | H3: Notiz | I3: Monat·intern
A4: Ja | B4: Founder Secondary (neuer Investor) | C4: Beteiligung | D4: Einnahme | E4: 50000 | F4: 46266 | G4: Theo | H4: Angabe von dir: 50.000 €, in etwa vier Wochen. Hier als Bruttoerlös – Steuer siehe nächste Zeile. | I4: =IF($B4="","",IF($F4="","",DATE(YEAR($F4),MONTH($F4),1))) -> 46266
A5: Ja | B5: Steuer auf Founder Secondary (Schätzung) | C5: Steuern | D5: Ausgabe | E5: 13200 | F5: 46692 | G5: Gemeinsam | H5: Rund 26 % Annahme (Teileinkünfteverfahren § 17 EStG bzw. Abgeltungsteuer), gerechnet auf 50.000 € Gewinn. Steuerlich ist das Theos Sache, bezahlt wird es aber vom gemeinsamen Konto. Höhe und Fälligkeit unbedingt mit dem Steuerberater klären – auch wegen möglicher Vorauszahlungen. | I5: =IF($B5="","",IF($F5="","",DATE(YEAR($F5),MONTH($F5),1))) -> 46692
A6: Ja | B6: Steuernachzahlung 2026 (zwei Jobs, StKl VI) | C6: Steuern | D6: Ausgabe | E6: 2800 | F6: 46692 | G6: Gemeinsam | H6: Schätzung. Der Lohnsteuerabzug aus StKl I + VI liegt unter der Jahressteuer; für 2026 zählt DESY erst ab Mitte März. Bei vollem Jahr sind es rund 3.700 € – für 2027 also entsprechend mehr. | I6: =IF($B6="","",IF($F6="","",DATE(YEAR($F6),MONTH($F6),1))) -> 46692
A7: Ja | B7: Jahressonderzahlung DESY 2026 (netto, Schätzung) | C7: Gehalt | D7: Einnahme | E7: 900 | F7: 46327 | G7: Theo | H7: TV-AVH sieht eine Jahressonderzahlung im November vor; in E13 fällt der Bemessungssatz niedrig aus. Angesetzt: rund ein halbes Monatsbrutto, netto in StKl VI. Bitte prüfen. | I7: =IF($B7="","",IF($F7="","",DATE(YEAR($F7),MONTH($F7),1))) -> 46327
A8: Ja | B8: Jahressonderzahlung DESY 2027 (netto, Schätzung) | C8: Gehalt | D8: Einnahme | E8: 900 | F8: 46692 | G8: Theo | H8: Wie Vorjahr. | I8: =IF($B8="","",IF($F8="","",DATE(YEAR($F8),MONTH($F8),1))) -> 46692
A9: Nein | B9: Hochzeit | C9: Familie | D9: Ausgabe | E9: 15000 | F9: 46569 | G9: Gemeinsam | H9: Beispielzeile mit Platzhalterbetrag – Betrag und Monat anpassen, dann auf „Ja“ stellen. | I9: =IF($B9="","",IF($F9="","",DATE(YEAR($F9),MONTH($F9),1))) -> 46569
A10: Nein | B10: Geldgeschenke Hochzeit | C10: Familie | D10: Einnahme | E10: 0 | F10: 46600 | G10: Gemeinsam | H10: Beispielzeile. | I10: =IF($B10="","",IF($F10="","",DATE(YEAR($F10),MONTH($F10),1))) -> 46600
A11: Nein | B11: Urlaub | C11: Reisen | D11: Ausgabe | E11: 0 | F11: 46600 | G11: Gemeinsam | H11: Beispielzeile. | I11: =IF($B11="","",IF($F11="","",DATE(YEAR($F11),MONTH($F11),1))) -> 46600
A12: Nein | B12: Größere Anschaffung (Möbel, Technik) | C12: Anschaffung | D12: Ausgabe | E12: 0 | F12: 46447 | G12: Gemeinsam | H12: Beispielzeile. | I12: =IF($B12="","",IF($F12="","",DATE(YEAR($F12),MONTH($F12),1))) -> 46447
I13: =IF($B13="","",IF($F13="","",DATE(YEAR($F13),MONTH($F13),1)))
I14: =IF($B14="","",IF($F14="","",DATE(YEAR($F14),MONTH($F14),1)))
I15: =IF($B15="","",IF($F15="","",DATE(YEAR($F15),MONTH($F15),1)))
I16: =IF($B16="","",IF($F16="","",DATE(YEAR($F16),MONTH($F16),1)))
I17: =IF($B17="","",IF($F17="","",DATE(YEAR($F17),MONTH($F17),1)))
I18: =IF($B18="","",IF($F18="","",DATE(YEAR($F18),MONTH($F18),1)))
I19: =IF($B19="","",IF($F19="","",DATE(YEAR($F19),MONTH($F19),1)))
I20: =IF($B20="","",IF($F20="","",DATE(YEAR($F20),MONTH($F20),1)))
I21: =IF($B21="","",IF($F21="","",DATE(YEAR($F21),MONTH($F21),1)))
I22: =IF($B22="","",IF($F22="","",DATE(YEAR($F22),MONTH($F22),1)))
I23: =IF($B23="","",IF($F23="","",DATE(YEAR($F23),MONTH($F23),1)))
I24: =IF($B24="","",IF($F24="","",DATE(YEAR($F24),MONTH($F24),1)))
... I43: =IF($B43="","",IF($F43="","",DATE(YEAR($F43),MONTH($F43),1)))
